{"v":"5.0.6","fr":60,"ip":0,"op":124,"w":720,"h":1280,"nm":"合成 1","ddd":0,"assets":[{"id":"comp_0","layers":[{"ddd":0,"ind":1,"ty":4,"nm":"形状图层 2","sr":1,"ks":{"o":{"a":0,"k":100,"ix":11},"r":{"a":0,"k":0,"ix":10},"p":{"a":0,"k":[359.978,517.978,0],"ix":2},"a":{"a":0,"k":[-0.022,-122.022,0],"ix":1},"s":{"a":0,"k":[93,93,100],"ix":6}},"ao":0,"shapes":[{"ty":"gr","it":[{"ty":"rc","d":1,"s":{"a":0,"k":[111.955,111.955],"ix":2},"p":{"a":0,"k":[0,0],"ix":3},"r":{"a":0,"k":18,"ix":4},"nm":"矩形路径 1","mn":"ADBE Vector Shape - Rect","hd":false},{"ty":"st","c":{"a":0,"k":[1,1,1,1],"ix":3},"o":{"a":0,"k":100,"ix":4},"w":{"a":0,"k":10,"ix":5},"lc":1,"lj":1,"ml":4,"nm":"描边 1","mn":"ADBE Vector Graphic - Stroke","hd":false},{"ty":"tr","p":{"a":0,"k":[-0.022,-122.022],"ix":2},"a":{"a":0,"k":[0,0],"ix":1},"s":{"a":0,"k":[111.886,111.886],"ix":3},"r":{"a":0,"k":0,"ix":6},"o":{"a":0,"k":100,"ix":7},"sk":{"a":0,"k":0,"ix":4},"sa":{"a":0,"k":0,"ix":5},"nm":"变换"}],"nm":"矩形 2","np":3,"cix":2,"ix":1,"mn":"ADBE Vector Group","hd":false}],"ip":0,"op":6001,"st":0,"bm":0},{"ddd":0,"ind":2,"ty":4,"nm":"“LOGO”轮廓","sr":1,"ks":{"o":{"a":0,"k":100,"ix":11},"r":{"a":0,"k":0,"ix":10},"p":{"a":0,"k":[360,546,0],"ix":2},"a":{"a":0,"k":[87,113,0],"ix":1},"s":{"a":0,"k":[83,83,100],"ix":6}},"ao":0,"shapes":[{"ty":"gr","it":[{"ty":"rc","d":1,"s":{"a":0,"k":[136.145,136.145],"ix":2},"p":{"a":0,"k":[0,0],"ix":3},"r":{"a":0,"k":7,"ix":4},"nm":"矩形路径 1","mn":"ADBE Vector Shape - Rect","hd":false},{"ty":"tr","p":{"a":0,"k":[86.398,78.663],"ix":2},"a":{"a":0,"k":[0,0],"ix":1},"s":{"a":0,"k":[100,100],"ix":3},"r":{"a":0,"k":0,"ix":6},"o":{"a":0,"k":100,"ix":7},"sk":{"a":0,"k":0,"ix":4},"sa":{"a":0,"k":0,"ix":5},"nm":"变换"}],"nm":"矩形 1","np":2,"cix":2,"ix":1,"mn":"ADBE Vector Group","hd":false},{"ty":"gr","it":[{"ind":0,"ty":"sh","ix":1,"ks":{"a":0,"k":{"i":[[0.635,-0.298],[0.724,-1.455],[-0.788,-3.09],[-5.123,-6.265],[-7.298,-2.518],[8.784,-8.981],[-0.478,-3.451],[-7.908,0.105],[-1.144,8.411],[-0.116,0.62],[-2.128,1.677],[-2.485,-3.254],[0.537,-2.119],[-0.364,-2.404],[3.241,-0.902],[2.6,0.665],[4.26,-1.252],[0.958,-1.46],[-0.37,-1.444],[-1.754,-1.335],[-6.39,0.368],[-2.363,12.045],[-0.866,6.907],[-2.573,6.876],[10.056,-3.088],[3.412,-7.099],[0,0],[1.419,4.642],[0.921,3.845],[-0.03,4.521],[2.491,0.484],[-2.867,-12.489],[0,0],[2.061,2.105],[4.246,5.186],[1.664,2.637],[1.457,2.479],[1.024,0.275],[0.303,0]],"o":[[-1.502,0.702],[-1.477,2.971],[2.026,7.933],[0,0],[0,0],[-8.784,8.983],[0,0],[0,0],[0.085,-0.62],[0.487,-2.586],[2.999,-2.362],[1.395,1.824],[2.282,0.654],[0.482,3.183],[-2.615,0.731],[-4.255,-1.086],[-1.64,0.485],[-0.984,1.501],[0.516,2.01],[5.087,3.863],[12.32,-0.706],[1.343,-6.845],[0.912,-7.275],[0,0],[0,0],[0,0],[-1.625,-4.575],[-1.153,-3.781],[-1.06,-4.413],[0.015,-2.301],[-4.43,-0.86],[0,0],[-1.762,-2.356],[-4.694,-4.791],[-1.976,-2.414],[-1.598,-2.525],[-0.533,-0.907],[-0.294,-0.079],[-0.698,0]],"v":[[-25.96,-45.072],[-29.441,-41.962],[-29.725,-32.199],[-17.424,-10.887],[-2.71,-9.921],[-23.66,-2.132],[-32.167,18.393],[-23.514,25.68],[-14.415,16.936],[-14.185,15.072],[-10.437,8.178],[0.18,8.777],[0.979,15.15],[5.767,19.976],[1.217,27.451],[-6.973,27.198],[-20.01,26.599],[-24.348,29.873],[-24.771,35.349],[-20.503,40.929],[-3.299,45.194],[22.512,23.314],[24.221,2.508],[29.471,-18.811],[22.59,-24.548],[14.417,-15.723],[18.062,1.355],[13.52,-12.488],[10.35,-23.917],[9.161,-36.889],[5.655,-41.995],[-3.413,-22.572],[8.473,-6.684],[1.952,-13.154],[-11.585,-28.04],[-17.154,-35.568],[-20.633,-43.492],[-23.025,-45.447],[-23.924,-45.561]],"c":true},"ix":2},"nm":"路径 1","mn":"ADBE Vector Shape - Group","hd":false},{"ty":"fl","c":{"a":0,"k":[1,1,1,1],"ix":4},"o":{"a":0,"k":100,"ix":5},"r":1,"nm":"填充 1","mn":"ADBE Vector Graphic - Fill","hd":false},{"ty":"tr","p":{"a":0,"k":[87.968,80.27],"ix":2},"a":{"a":0,"k":[0,0],"ix":1},"s":{"a":0,"k":[100,100],"ix":3},"r":{"a":0,"k":0,"ix":6},"o":{"a":0,"k":100,"ix":7},"sk":{"a":0,"k":0,"ix":4},"sa":{"a":0,"k":0,"ix":5},"nm":"变换"}],"nm":"组 1","np":2,"cix":2,"ix":2,"mn":"ADBE Vector Group","hd":false},{"ty":"gr","it":[{"ind":0,"ty":"sh","ix":1,"ks":{"a":0,"k":{"i":[[0,0],[0,0],[0,0],[0,0],[0,0],[0,0],[0,0],[0,0],[0,0],[0,0],[0,0],[0,0],[0,0]],"o":[[0,0],[0,0],[0,0],[0,0],[0,0],[0,0],[0,0],[0,0],[0,0],[0,0],[0,0],[0,0],[0,0]],"v":[[25.927,-20.64],[25.927,20.109],[34.857,20.109],[34.857,11.943],[37.375,9.424],[43.629,20.109],[53.857,20.109],[43.152,3.22],[53.195,-8.578],[42.489,-8.578],[35.758,-0.2],[34.857,0.994],[34.857,-20.64]],"c":true},"ix":2},"nm":"路径 1","mn":"ADBE Vector Shape - Group","hd":false},{"ind":1,"ty":"sh","ix":2,"ks":{"a":0,"k":{"i":[[0,0],[0,0],[0,0],[0,0]],"o":[[0,0],[0,0],[0,0],[0,0]],"v":[[-2.945,20.109],[6.012,20.109],[6.012,-20.613],[-2.945,-20.613]],"c":true},"ix":2},"nm":"路径 2","mn":"ADBE Vector Shape - Group","hd":false},{"ind":2,"ty":"sh","ix":3,"ks":{"a":0,"k":{"i":[[0,0]],"o":[[0,0]],"v":[[-2.945,-20.613]],"c":false},"ix":2},"nm":"路径 3","mn":"ADBE Vector Shape - Group","hd":false},{"ind":3,"ty":"sh","ix":4,"ks":{"a":0,"k":{"i":[[0.602,-0.212],[0.442,-0.389],[0.238,-0.531],[0,-0.636],[-0.239,-0.53],[-0.441,-0.389],[-0.6,-0.211],[-0.742,0],[-0.601,0.213],[-0.442,0.388],[-0.239,0.53],[0,0.636],[0.238,0.531],[0.442,0.388],[0.6,0.212],[0.742,0]],"o":[[-0.6,0.212],[-0.441,0.388],[-0.239,0.531],[0,0.636],[0.238,0.53],[0.442,0.388],[0.602,0.213],[0.742,0],[0.6,-0.211],[0.442,-0.389],[0.238,-0.53],[0,-0.636],[-0.239,-0.531],[-0.442,-0.389],[-0.601,-0.212],[-0.742,0]],"v":[[14.1,-20.004],[12.537,-19.102],[11.518,-17.724],[11.159,-15.974],[11.518,-14.224],[12.537,-12.845],[14.1,-11.945],[16.115,-11.626],[18.129,-11.945],[19.692,-12.845],[20.713,-14.224],[21.07,-15.974],[20.713,-17.724],[19.692,-19.102],[18.129,-20.004],[16.115,-20.322]],"c":true},"ix":2},"nm":"路径 4","mn":"ADBE Vector Shape - Group","hd":false},{"ind":4,"ty":"sh","ix":5,"ks":{"a":0,"k":{"i":[[0,0],[0,0],[0,0],[0,0],[0,0],[0,0],[0,0],[0,0],[0,0],[0,0],[0,0],[0,0],[0,0]],"o":[[0,0],[0,0],[0,0],[0,0],[0,0],[0,0],[0,0],[0,0],[0,0],[0,0],[0,0],[0,0],[0,0]],"v":[[-44.007,-18.493],[-48.432,5.714],[-53.812,-18.493],[-61.709,-18.493],[-67.008,5.714],[-71.434,-18.493],[-80.682,-18.493],[-72.468,20.109],[-62.849,20.109],[-57.787,-1.896],[-52.619,20.109],[-42.974,20.109],[-34.786,-18.493]],"c":true},"ix":2},"nm":"路径 5","mn":"ADBE Vector Shape - Group","hd":false},{"ind":5,"ty":"sh","ix":6,"ks":{"a":0,"k":{"i":[[1.723,-0.76],[1.157,-1.326],[0.575,-1.812],[0,-2.086],[0,0],[-0.663,-1.679],[-1.253,-1.273],[-1.837,-0.742],[-2.332,0],[-1.183,0.291],[-0.954,0.468],[-0.716,0.601],[-0.459,0.636],[0,0],[1.175,-0.459],[1.219,0],[1.077,0.919],[0.318,1.61],[0,0],[0,0],[0.593,1.733],[1.122,1.219],[1.617,0.654],[2.031,0]],"o":[[-1.722,0.76],[-1.157,1.326],[-0.574,1.812],[0,0],[0,1.891],[0.662,1.68],[1.255,1.272],[1.837,0.742],[1.378,0],[1.184,-0.292],[0.954,-0.468],[0.715,-0.601],[0,0],[-0.847,1.061],[-1.175,0.459],[-1.713,0],[-1.079,-0.919],[0,0],[0,0],[0,-2.156],[-0.591,-1.732],[-1.122,-1.22],[-1.616,-0.654],[-2.297,0]],"v":[[61.615,-7.967],[57.296,-4.839],[54.699,-0.133],[53.838,5.714],[53.838,6.72],[54.832,12.076],[57.706,16.503],[62.344,19.525],[68.598,20.639],[72.44,20.202],[75.647,19.061],[78.151,17.457],[79.913,15.602],[75.832,10.776],[72.798,13.056],[69.207,13.746],[65.021,12.367],[62.927,8.576],[80.682,8.576],[80.682,4.944],[79.793,-0.889],[77.223,-5.316],[73.116,-8.127],[67.644,-9.108]],"c":true},"ix":2},"nm":"路径 6","mn":"ADBE Vector Shape - Group","hd":false},{"ind":6,"ty":"sh","ix":7,"ks":{"a":0,"k":{"i":[[-0.212,0.636],[-0.363,0.459],[-0.548,0.266],[-0.759,0],[-0.76,-0.786],[0.035,-1.432],[0,0],[0,0]],"o":[[0.212,-0.637],[0.361,-0.46],[0.548,-0.265],[1.413,0],[0.76,0.787],[0,0],[0,0],[0.106,-0.743]],"v":[[63.404,0.914],[64.266,-0.73],[65.63,-1.816],[67.591,-2.215],[70.85,-1.035],[71.937,2.293],[71.937,2.982],[62.927,2.982]],"c":true},"ix":2},"nm":"路径 7","mn":"ADBE Vector Shape - Group","hd":false},{"ind":7,"ty":"sh","ix":8,"ks":{"a":0,"k":{"i":[[1.722,-0.76],[1.157,-1.326],[0.574,-1.812],[0,-2.086],[0,0],[-0.663,-1.679],[-1.254,-1.273],[-1.837,-0.742],[-2.332,0],[-1.183,0.291],[-0.954,0.468],[-0.716,0.601],[-0.459,0.636],[0,0],[1.176,-0.459],[1.219,0],[1.077,0.919],[0.318,1.61],[0,0],[0,0],[0.592,1.733],[1.122,1.219],[1.616,0.654],[2.031,0]],"o":[[-1.723,0.76],[-1.158,1.326],[-0.574,1.812],[0,0],[0,1.891],[0.662,1.68],[1.255,1.272],[1.837,0.742],[1.378,0],[1.184,-0.292],[0.954,-0.468],[0.715,-0.601],[0,0],[-0.848,1.061],[-1.174,0.459],[-1.713,0],[-1.079,-0.919],[0,0],[0,0],[0,-2.156],[-0.591,-1.732],[-1.122,-1.22],[-1.616,-0.654],[-2.297,0]],"v":[[-25.782,-7.967],[-30.101,-4.839],[-32.698,-0.133],[-33.559,5.714],[-33.559,6.72],[-32.565,12.076],[-29.691,16.503],[-25.053,19.525],[-18.799,20.639],[-14.957,20.202],[-11.75,19.061],[-9.246,17.457],[-7.484,15.602],[-11.565,10.776],[-14.6,13.056],[-18.19,13.746],[-22.376,12.367],[-24.47,8.576],[-6.716,8.576],[-6.716,4.944],[-7.604,-0.889],[-10.174,-5.316],[-14.281,-8.127],[-19.753,-9.108]],"c":true},"ix":2},"nm":"路径 8","mn":"ADBE Vector Shape - Group","hd":false},{"ind":8,"ty":"sh","ix":9,"ks":{"a":0,"k":{"i":[[-0.212,0.636],[-0.362,0.459],[-0.548,0.266],[-0.76,0],[-0.76,-0.786],[0.036,-1.432],[0,0],[0,0]],"o":[[0.212,-0.637],[0.362,-0.46],[0.547,-0.265],[1.413,0],[0.759,0.787],[0,0],[0,0],[0.105,-0.743]],"v":[[-23.993,0.914],[-23.132,-0.73],[-21.767,-1.816],[-19.806,-2.215],[-16.547,-1.035],[-15.461,2.293],[-15.461,2.982],[-24.47,2.982]],"c":true},"ix":2},"nm":"路径 9","mn":"ADBE Vector Shape - Group","hd":false},{"ind":9,"ty":"sh","ix":10,"ks":{"a":0,"k":{"i":[[0,0],[0,0],[0,0],[0,0]],"o":[[0,0],[0,0],[0,0],[0,0]],"v":[[11.689,20.109],[20.646,20.109],[20.646,-8.578],[11.689,-8.578]],"c":true},"ix":2},"nm":"路径 10","mn":"ADBE Vector Shape - Group","hd":false},{"ty":"mm","mm":1,"nm":"合并路径 1","mn":"ADBE Vector Filter - Merge","hd":false},{"ty":"fl","c":{"a":0,"k":[0.19199999641,0.19199999641,0.19199999641,1],"ix":4},"o":{"a":0,"k":100,"ix":5},"r":1,"nm":"填充 1","mn":"ADBE Vector Graphic - Fill","hd":false},{"ty":"tr","p":{"a":0,"k":[86.785,194.53],"ix":2},"a":{"a":0,"k":[0,0],"ix":1},"s":{"a":0,"k":[100,100],"ix":3},"r":{"a":0,"k":0,"ix":6},"o":{"a":0,"k":100,"ix":7},"sk":{"a":0,"k":0,"ix":4},"sa":{"a":0,"k":0,"ix":5},"nm":"变换"}],"nm":"组 2","np":12,"cix":2,"ix":3,"mn":"ADBE Vector Group","hd":false},{"ty":"gr","it":[{"ind":0,"ty":"sh","ix":1,"ks":{"a":0,"k":{"i":[[2.614,-0.808],[0,1.03],[-1.728,0.638],[-18.258,6.777],[-22.435,8.295],[1.815,-0.657],[23.089,-9.143],[15.647,-6.6]],"o":[[0,-1.03],[1.836,-0.347],[18.269,-6.746],[22.425,-8.322],[1.242,2.289],[-23.356,8.465],[-15.791,6.253],[-2.509,1.058]],"v":[[-64.396,24.721],[-64.396,21.631],[-58.902,20.553],[-4.148,0.17],[63.154,-24.721],[61.121,-21.114],[-8.858,4.511],[-56.568,22.261]],"c":true},"ix":2},"nm":"路径 1","mn":"ADBE Vector Shape - Group","hd":false},{"ty":"fl","c":{"a":0,"k":[0.995999983245,0.725,0,1],"ix":4},"o":{"a":0,"k":100,"ix":5},"r":1,"nm":"填充 1","mn":"ADBE Vector Graphic - Fill","hd":false},{"ty":"tr","p":{"a":0,"k":[83.813,55.993],"ix":2},"a":{"a":0,"k":[0,0],"ix":1},"s":{"a":0,"k":[100,100],"ix":3},"r":{"a":0,"k":0,"ix":6},"o":{"a":0,"k":100,"ix":7},"sk":{"a":0,"k":0,"ix":4},"sa":{"a":0,"k":0,"ix":5},"nm":"变换"}],"nm":"组 3","np":2,"cix":2,"ix":4,"mn":"ADBE Vector Group","hd":false},{"ty":"gr","it":[{"ind":0,"ty":"sh","ix":1,"ks":{"a":0,"k":{"i":[[-4.463,0],[-4.807,0],[-17.51,-0.058],[0.626,-0.001],[44.29,-0.085],[-0.005,2.211],[-0.025,44.29],[-1.644,-0.352],[-0.057,-5.494],[0,-2.747],[0,-2.06],[0,-1.717],[0,-2.747],[0,-3.433],[0,-2.403],[0,-1.03],[0,-0.687],[0.712,-1.03],[0,-1.03],[0,0],[0,-1.374],[0,-1.716],[0,-1.374],[0,-1.717],[0,-1.717],[0,-1.374],[0,-1.03],[0,-1.03],[0,-1.029],[0,-1.03],[0,-1.717],[0,-1.03],[0,-0.686],[0.079,-2.389],[-1.65,0.387],[-4.463,0],[-2.747,0],[-3.433,0],[-3.777,0],[-3.434,0]],"o":[[4.807,0],[17.51,0.057],[0.352,1.644],[-44.29,0.024],[-2.211,0.004],[0.084,-44.291],[0,-0.625],[0.058,5.493],[0,2.746],[0,2.06],[0,1.716],[0,2.747],[0,3.434],[0,2.404],[0,1.03],[0,0.686],[0.755,1.03],[0,1.03],[0,0],[0,1.373],[0,1.716],[0,1.374],[0,1.716],[0,1.716],[0,1.373],[0,1.03],[0,1.031],[0,1.03],[0,1.031],[0,1.717],[0,1.03],[0,0.687],[-0.055,2.39],[-0.049,1.464],[4.464,0],[2.747,0],[3.434,0],[3.777,0],[3.433,0],[4.463,0]],"v":[[1.677,67.163],[16.097,67.163],[68.627,67.335],[67.082,68.343],[-65.789,68.428],[-68.427,65.79],[-68.342,-67.082],[-67.335,-68.627],[-67.163,-52.146],[-67.163,-43.906],[-67.163,-37.726],[-67.163,-32.576],[-67.163,-24.336],[-67.163,-14.036],[-67.163,-6.826],[-67.163,-3.736],[-67.163,-1.676],[-67.163,1.414],[-67.163,4.504],[-67.163,7.594],[-67.163,11.715],[-67.163,16.864],[-67.163,20.985],[-67.163,26.135],[-67.163,31.285],[-67.163,35.405],[-67.163,38.494],[-67.163,41.585],[-67.163,44.674],[-67.163,47.765],[-67.163,52.915],[-67.163,56.005],[-67.162,58.065],[-67.334,65.235],[-65.274,67.163],[-51.884,67.163],[-43.644,67.163],[-33.344,67.163],[-22.013,67.163],[-11.713,67.163]],"c":true},"ix":2},"nm":"路径 1","mn":"ADBE Vector Shape - Group","hd":false},{"ty":"fl","c":{"a":0,"k":[0.995999983245,0.995999983245,0.995999983245,1],"ix":4},"o":{"a":0,"k":100,"ix":5},"r":1,"nm":"填充 1","mn":"ADBE Vector Graphic - Fill","hd":false},{"ty":"tr","p":{"a":0,"k":[86.58,79.3],"ix":2},"a":{"a":0,"k":[0,0],"ix":1},"s":{"a":0,"k":[100,100],"ix":3},"r":{"a":0,"k":0,"ix":6},"o":{"a":0,"k":100,"ix":7},"sk":{"a":0,"k":0,"ix":4},"sa":{"a":0,"k":0,"ix":5},"nm":"变换"}],"nm":"组 4","np":2,"cix":2,"ix":5,"mn":"ADBE Vector Group","hd":false},{"ty":"gr","it":[{"ind":0,"ty":"sh","ix":1,"ks":{"a":0,"k":{"i":[[4.807,1.131],[-5.497,2.155],[-12.296,4.685],[-4.227,2.776],[0,0],[16.057,-5.566],[1.096,-1.672]],"o":[[4.491,-4.348],[12.249,-4.802],[4.619,-1.759],[0,0],[-16.365,4.71],[-1.743,0.605],[-4.807,1.131]],"v":[[-33.475,12.739],[-17.402,5.128],[19.62,-8.574],[33.475,-13.87],[33.475,-7.69],[-14.465,9.646],[-19.055,12.739]],"c":true},"ix":2},"nm":"路径 1","mn":"ADBE Vector Shape - Group","hd":false},{"ty":"fl","c":{"a":0,"k":[0.995999983245,0.583999992819,0,1],"ix":4},"o":{"a":0,"k":100,"ix":5},"r":1,"nm":"填充 1","mn":"ADBE Vector Graphic - Fill","hd":false},{"ty":"tr","p":{"a":0,"k":[121.732,133.724],"ix":2},"a":{"a":0,"k":[0,0],"ix":1},"s":{"a":0,"k":[100,100],"ix":3},"r":{"a":0,"k":0,"ix":6},"o":{"a":0,"k":100,"ix":7},"sk":{"a":0,"k":0,"ix":4},"sa":{"a":0,"k":0,"ix":5},"nm":"变换"}],"nm":"组 5","np":2,"cix":2,"ix":6,"mn":"ADBE Vector Group","hd":false},{"ty":"gr","it":[{"ind":0,"ty":"sh","ix":1,"ks":{"a":0,"k":{"i":[[4.031,1.491],[-2.09,0.767],[-24.887,9.158],[0,0],[3.136,-1.042],[11.495,-4.29],[8.974,-2.67]],"o":[[1.37,-1.999],[24.893,-9.143],[0,0],[-1.436,2.956],[-11.644,3.87],[-8.76,3.269],[-4.099,-0.376]],"v":[[-40.171,14.619],[-34.494,11.355],[40.171,-16.11],[40.171,-11.99],[33.202,-6.552],[-1.319,6.213],[-27.862,15.298]],"c":true},"ix":2},"nm":"路径 1","mn":"ADBE Vector Shape - Group","hd":false},{"ty":"fl","c":{"a":0,"k":[0.995999983245,0.592000026329,0,1],"ix":4},"o":{"a":0,"k":100,"ix":5},"r":1,"nm":"填充 1","mn":"ADBE Vector Graphic - Fill","hd":false},{"ty":"tr","p":{"a":0,"k":[115.037,131.844],"ix":2},"a":{"a":0,"k":[0,0],"ix":1},"s":{"a":0,"k":[100,100],"ix":3},"r":{"a":0,"k":0,"ix":6},"o":{"a":0,"k":100,"ix":7},"sk":{"a":0,"k":0,"ix":4},"sa":{"a":0,"k":0,"ix":5},"nm":"变换"}],"nm":"组 6","np":2,"cix":2,"ix":7,"mn":"ADBE Vector Group","hd":false},{"ty":"gr","it":[{"ind":0,"ty":"sh","ix":1,"ks":{"a":0,"k":{"i":[[3.043,1.49],[-5.632,2.248],[-14.892,5.511],[-9.803,3.52],[0,0],[2.505,-0.869],[12.92,-4.445],[12.895,-2.387]],"o":[[4.561,-4.684],[14.745,-5.887],[9.767,-3.615],[0,0],[-1.17,2.575],[-12.929,4.483],[-12.263,4.218],[-3.128,-0.366]],"v":[[-45.32,16.679],[-28.646,9.234],[15.92,-7.592],[45.32,-18.17],[45.32,-14.049],[39.376,-9.543],[0.844,4.584],[-35.915,17.354]],"c":true},"ix":2},"nm":"路径 1","mn":"ADBE Vector Shape - Group","hd":false},{"ty":"fl","c":{"a":0,"k":[0.995999983245,0.596000043084,0,1],"ix":4},"o":{"a":0,"k":100,"ix":5},"r":1,"nm":"填充 1","mn":"ADBE Vector Graphic - Fill","hd":false},{"ty":"tr","p":{"a":0,"k":[109.887,129.783],"ix":2},"a":{"a":0,"k":[0,0],"ix":1},"s":{"a":0,"k":[100,100],"ix":3},"r":{"a":0,"k":0,"ix":6},"o":{"a":0,"k":100,"ix":7},"sk":{"a":0,"k":0,"ix":4},"sa":{"a":0,"k":0,"ix":5},"nm":"变换"}],"nm":"组 7","np":2,"cix":2,"ix":8,"mn":"ADBE Vector Group","hd":false},{"ty":"gr","it":[{"ind":0,"ty":"sh","ix":1,"ks":{"a":0,"k":{"i":[[-0.965,1.03],[-10.135,3.603],[-15.856,5.902],[-17.604,6.611],[-1.777,-0.049],[0,0],[6.247,-2.282],[21.204,-7.658],[18.048,-5.926]],"o":[[10.618,-2.227],[15.939,-5.667],[17.622,-6.559],[1.606,-0.604],[0,0],[-6.33,2.055],[-21.172,7.733],[-17.843,6.445],[-0.964,-1.03]],"v":[[-67.413,23.2],[-36.979,12.464],[10.632,-5.123],[63.472,-24.877],[68.378,-26.241],[68.378,-23.151],[49.401,-16.953],[-14.04,6.456],[-67.413,26.29]],"c":true},"ix":2},"nm":"路径 1","mn":"ADBE Vector Shape - Group","hd":false},{"ty":"fl","c":{"a":0,"k":[0.995999983245,0.658999992819,0,1],"ix":4},"o":{"a":0,"k":100,"ix":5},"r":1,"nm":"填充 1","mn":"ADBE Vector Graphic - Fill","hd":false},{"ty":"tr","p":{"a":0,"k":[86.83,100.774],"ix":2},"a":{"a":0,"k":[0,0],"ix":1},"s":{"a":0,"k":[100,100],"ix":3},"r":{"a":0,"k":0,"ix":6},"o":{"a":0,"k":100,"ix":7},"sk":{"a":0,"k":0,"ix":4},"sa":{"a":0,"k":0,"ix":5},"nm":"变换"}],"nm":"组 8","np":2,"cix":2,"ix":9,"mn":"ADBE Vector Group","hd":false},{"ty":"gr","it":[{"ind":0,"ty":"sh","ix":1,"ks":{"a":0,"k":{"i":[[0,0],[32.659,-11.907],[12.605,-4.914],[-0.965,1.03],[-12.496,4.597],[-22.937,8.455],[-10.091,2.683]],"o":[[-32.57,12.15],[-12.709,4.634],[-0.965,-1.03],[12.498,-4.592],[22.942,-8.44],[9.769,-3.602],[0,0]],"v":[[68.378,-24.206],[-29.363,12.165],[-67.412,26.266],[-67.412,23.176],[-29.919,9.398],[38.904,-15.936],[68.378,-26.266]],"c":true},"ix":2},"nm":"路径 1","mn":"ADBE Vector Shape - Group","hd":false},{"ty":"fl","c":{"a":0,"k":[0.995999983245,0.736999990426,0,1],"ix":4},"o":{"a":0,"k":100,"ix":5},"r":1,"nm":"填充 1","mn":"ADBE Vector Graphic - Fill","hd":false},{"ty":"tr","p":{"a":0,"k":[86.83,49.298],"ix":2},"a":{"a":0,"k":[0,0],"ix":1},"s":{"a":0,"k":[100,100],"ix":3},"r":{"a":0,"k":0,"ix":6},"o":{"a":0,"k":100,"ix":7},"sk":{"a":0,"k":0,"ix":4},"sa":{"a":0,"k":0,"ix":5},"nm":"变换"}],"nm":"组 9","np":2,"cix":2,"ix":10,"mn":"ADBE Vector Group","hd":false},{"ty":"gr","it":[{"ind":0,"ty":"sh","ix":1,"ks":{"a":0,"k":{"i":[[-0.964,1.03],[-18.135,6.728],[-15.61,5.677],[-8.626,3.837],[-2.806,-0.216],[0,0],[9.543,-3.274],[20.408,-7.409],[11.95,-5.988],[2.885,-1.072]],"o":[[18.463,-5.816],[15.574,-5.777],[8.853,-3.22],[2.53,-1.126],[0,0],[-9.505,3.384],[-20.539,7.049],[-12.487,4.534],[-2.839,1.422],[-0.964,-1.03]],"v":[[-67.413,22.768],[-12.816,3.115],[33.884,-14.275],[60.37,-24.124],[68.377,-25.643],[68.377,-23.583],[39.854,-13.451],[-21.219,9.178],[-58.531,23.43],[-67.413,25.859]],"c":true},"ix":2},"nm":"路径 1","mn":"ADBE Vector Shape - Group","hd":false},{"ty":"fl","c":{"a":0,"k":[0.995999983245,0.717999985639,0,1],"ix":4},"o":{"a":0,"k":100,"ix":5},"r":1,"nm":"填充 1","mn":"ADBE Vector Graphic - Fill","hd":false},{"ty":"tr","p":{"a":0,"k":[86.83,61.036],"ix":2},"a":{"a":0,"k":[0,0],"ix":1},"s":{"a":0,"k":[100,100],"ix":3},"r":{"a":0,"k":0,"ix":6},"o":{"a":0,"k":100,"ix":7},"sk":{"a":0,"k":0,"ix":4},"sa":{"a":0,"k":0,"ix":5},"nm":"变换"}],"nm":"组 10","np":2,"cix":2,"ix":11,"mn":"ADBE Vector Group","hd":false},{"ty":"gr","it":[{"ind":0,"ty":"sh","ix":1,"ks":{"a":0,"k":{"i":[[0,0],[1.183,-0.438],[12.44,-4.538],[0.847,-0.054],[-0.7,5.501]],"o":[[-0.265,1.279],[-12.42,4.593],[-0.765,0.279],[-1.271,-5.481],[0,0]],"v":[[21.665,-8.284],[19.42,-5.713],[-17.863,8.005],[-20.394,8.197],[-20.566,-8.284]],"c":true},"ix":2},"nm":"路径 1","mn":"ADBE Vector Shape - Group","hd":false},{"ty":"fl","c":{"a":0,"k":[0.995999983245,0.816000007181,0,1],"ix":4},"o":{"a":0,"k":100,"ix":5},"r":1,"nm":"填充 1","mn":"ADBE Vector Graphic - Fill","hd":false},{"ty":"tr","p":{"a":0,"k":[39.811,18.957],"ix":2},"a":{"a":0,"k":[0,0],"ix":1},"s":{"a":0,"k":[100,100],"ix":3},"r":{"a":0,"k":0,"ix":6},"o":{"a":0,"k":100,"ix":7},"sk":{"a":0,"k":0,"ix":4},"sa":{"a":0,"k":0,"ix":5},"nm":"变换"}],"nm":"组 11","np":2,"cix":2,"ix":12,"mn":"ADBE Vector Group","hd":false},{"ty":"gr","it":[{"ind":0,"ty":"sh","ix":1,"ks":{"a":0,"k":{"i":[[0,0],[7.903,-2.679],[19.29,-7.123],[8.468,-3.263],[1.229,-1.825],[2.746,1.111],[-1.986,0.733],[-19.278,7.085],[-19.292,7.061]],"o":[[-8.577,0.659],[-19.469,6.597],[-8.513,3.144],[-1.897,0.731],[-2.747,1.111],[1.159,-1.814],[19.271,-7.107],[19.283,-7.087],[0,0]],"v":[[60.256,-19.525],[36.505,-11.533],[-21.449,9.596],[-46.92,19.209],[-52.016,22.534],[-60.256,22.534],[-55.43,18.868],[2.381,-2.455],[60.256,-23.645]],"c":true},"ix":2},"nm":"路径 1","mn":"ADBE Vector Shape - Group","hd":false},{"ty":"fl","c":{"a":0,"k":[0.995999983245,0.616000007181,0,1],"ix":4},"o":{"a":0,"k":100,"ix":5},"r":1,"nm":"填充 1","mn":"ADBE Vector Graphic - Fill","hd":false},{"ty":"tr","p":{"a":0,"k":[94.952,123.929],"ix":2},"a":{"a":0,"k":[0,0],"ix":1},"s":{"a":0,"k":[100,100],"ix":3},"r":{"a":0,"k":0,"ix":6},"o":{"a":0,"k":100,"ix":7},"sk":{"a":0,"k":0,"ix":4},"sa":{"a":0,"k":0,"ix":5},"nm":"变换"}],"nm":"组 12","np":2,"cix":2,"ix":13,"mn":"ADBE Vector Group","hd":false},{"ty":"gr","it":[{"ind":0,"ty":"sh","ix":1,"ks":{"a":0,"k":{"i":[[0,0],[2.747,-0.687],[4.206,-1.47],[30.416,-10.53],[5.964,-2.616],[2.353,1.807],[-0.205,0.805],[-5.877,2.046],[-20.198,7.425],[-17.71,6.714],[-1.906,-1.014]],"o":[[-2.747,0.687],[-3.168,3.866],[-30.39,10.62],[-6.152,2.13],[-2.108,0.924],[-0.426,-0.754],[5.005,-4.052],[20.334,-7.081],[17.774,-6.535],[1.698,-0.643],[0,0]],"v":[[68.263,-22.675],[60.023,-20.615],[47.731,-14.757],[-42.847,18.676],[-61.056,25.65],[-67.837,26.002],[-68.027,23.651],[-51.015,15.761],[9.504,-6.739],[62.834,-26.33],[68.263,-26.795]],"c":true},"ix":2},"nm":"路径 1","mn":"ADBE Vector Shape - Group","hd":false},{"ty":"fl","c":{"a":0,"k":[0.995999983245,0.732999973671,0,1],"ix":4},"o":{"a":0,"k":100,"ix":5},"r":1,"nm":"填充 1","mn":"ADBE Vector Graphic - Fill","hd":false},{"ty":"tr","p":{"a":0,"k":[86.945,51.887],"ix":2},"a":{"a":0,"k":[0,0],"ix":1},"s":{"a":0,"k":[100,100],"ix":3},"r":{"a":0,"k":0,"ix":6},"o":{"a":0,"k":100,"ix":7},"sk":{"a":0,"k":0,"ix":4},"sa":{"a":0,"k":0,"ix":5},"nm":"变换"}],"nm":"组 13","np":2,"cix":2,"ix":14,"mn":"ADBE Vector Group","hd":false},{"ty":"gr","it":[{"ind":0,"ty":"sh","ix":1,"ks":{"a":0,"k":{"i":[[0,0],[20.708,-7.678],[20.827,-7.882],[3.74,-1.229],[-0.965,1.03],[-22.168,8.114],[-16.066,5.842],[-5.336,2.274],[-1.738,-0.042]],"o":[[-20.395,8.526],[-20.879,7.743],[-3.679,1.392],[-0.965,-1.03],[22.141,-8.186],[16.053,-5.876],[5.451,-1.982],[1.63,-0.694],[0,0]],"v":[[68.378,-24.185],[6.252,-1.15],[-56.201,22.576],[-67.412,26.286],[-67.412,23.197],[-0.982,-1.344],[47.264,-18.734],[63.457,-25.113],[68.378,-26.245]],"c":true},"ix":2},"nm":"路径 1","mn":"ADBE Vector Shape - Group","hd":false},{"ty":"fl","c":{"a":0,"k":[0.995999983245,0.670999983245,0,1],"ix":4},"o":{"a":0,"k":100,"ix":5},"r":1,"nm":"填充 1","mn":"ADBE Vector Graphic - Fill","hd":false},{"ty":"tr","p":{"a":0,"k":[86.83,91.508],"ix":2},"a":{"a":0,"k":[0,0],"ix":1},"s":{"a":0,"k":[100,100],"ix":3},"r":{"a":0,"k":0,"ix":6},"o":{"a":0,"k":100,"ix":7},"sk":{"a":0,"k":0,"ix":4},"sa":{"a":0,"k":0,"ix":5},"nm":"变换"}],"nm":"组 14","np":2,"cix":2,"ix":15,"mn":"ADBE Vector Group","hd":false},{"ty":"gr","it":[{"ind":0,"ty":"sh","ix":1,"ks":{"a":0,"k":{"i":[[0,0],[5.412,-2],[17.347,-6.18],[9.882,-4.666],[0.794,-1.237],[3.163,-0.331],[-1.877,0.717],[-4.373,1.4],[-16.011,5.806],[-13.543,5.604],[-2.588,-2.657]],"o":[[-5.808,0.876],[-17.275,6.386],[-10.272,3.66],[-1.244,0.587],[-3.087,1.486],[-2.485,-2.798],[4.305,-1.645],[16.237,-5.199],[13.753,-4.988],[2.36,-0.976],[0,0]],"v":[[56.988,-17.354],[40.635,-11.64],[-11.103,7.749],[-41.62,19.433],[-44.983,21.615],[-54.503,22.272],[-52.607,17.708],[-39.787,12.568],[8.241,-4.907],[49.424,-20.223],[56.988,-20.444]],"c":true},"ix":2},"nm":"路径 1","mn":"ADBE Vector Shape - Group","hd":false},{"ty":"fl","c":{"a":0,"k":[0.995999983245,0.611999990426,0,1],"ix":4},"o":{"a":0,"k":100,"ix":5},"r":1,"nm":"填充 1","mn":"ADBE Vector Graphic - Fill","hd":false},{"ty":"tr","p":{"a":0,"k":[98.22,124.848],"ix":2},"a":{"a":0,"k":[0,0],"ix":1},"s":{"a":0,"k":[100,100],"ix":3},"r":{"a":0,"k":0,"ix":6},"o":{"a":0,"k":100,"ix":7},"sk":{"a":0,"k":0,"ix":4},"sa":{"a":0,"k":0,"ix":5},"nm":"变换"}],"nm":"组 15","np":2,"cix":2,"ix":16,"mn":"ADBE Vector Group","hd":false},{"ty":"gr","it":[{"ind":0,"ty":"sh","ix":1,"ks":{"a":0,"k":{"i":[[0,0],[6.554,-2.627],[14.451,-5.238],[0.298,2.511],[-2.643,0.899],[-11.854,2.261],[-0.525,0.448]],"o":[[-5.357,5.314],[-14.26,5.715],[-1.435,-2.416],[1.233,-3.162],[11.321,-3.848],[0.689,-0.131],[0,0]],"v":[[32.047,-12.361],[12.682,-3.499],[-30.612,12.361],[-31.272,4.799],[-24.305,0.122],[9.687,-11.34],[11.447,-12.361]],"c":true},"ix":2},"nm":"路径 1","mn":"ADBE Vector Shape - Group","hd":false},{"ty":"fl","c":{"a":0,"k":[0.995999983245,0.804000016755,0,1],"ix":4},"o":{"a":0,"k":100,"ix":5},"r":1,"nm":"填充 1","mn":"ADBE Vector Graphic - Fill","hd":false},{"ty":"tr","p":{"a":0,"k":[50.029,23.033],"ix":2},"a":{"a":0,"k":[0,0],"ix":1},"s":{"a":0,"k":[100,100],"ix":3},"r":{"a":0,"k":0,"ix":6},"o":{"a":0,"k":100,"ix":7},"sk":{"a":0,"k":0,"ix":4},"sa":{"a":0,"k":0,"ix":5},"nm":"变换"}],"nm":"组 16","np":2,"cix":2,"ix":17,"mn":"ADBE Vector Group","hd":false},{"ty":"gr","it":[{"ind":0,"ty":"sh","ix":1,"ks":{"a":0,"k":{"i":[[-1.587,-1.761],[0,0],[2.474,-0.872],[17.013,-6.76],[11.295,-3.954],[3.367,0.116],[-1.968,0.937],[-8.952,3.356],[-9.125,3.818],[-12.616,5.695]],"o":[[0,0],[-1.133,2.683],[-17.269,6.089],[-11.135,4.424],[-3.371,0.012],[-1.968,-3.268],[8.655,-4.119],[9.27,-3.475],[12.76,-5.341],[1.711,-0.773]],"v":[[51.704,-18.976],[51.704,-14.856],[45.652,-10.583],[-5.896,8.386],[-39.629,20.659],[-49.736,20.621],[-46.954,15.698],[-20.199,5.338],[7.71,-4.834],[46.488,-19.458]],"c":true},"ix":2},"nm":"路径 1","mn":"ADBE Vector Shape - Group","hd":false},{"ty":"fl","c":{"a":0,"k":[0.995999983245,0.603999956916,0,1],"ix":4},"o":{"a":0,"k":100,"ix":5},"r":1,"nm":"填充 1","mn":"ADBE Vector Graphic - Fill","hd":false},{"ty":"tr","p":{"a":0,"k":[103.504,126.47],"ix":2},"a":{"a":0,"k":[0,0],"ix":1},"s":{"a":0,"k":[100,100],"ix":3},"r":{"a":0,"k":0,"ix":6},"o":{"a":0,"k":100,"ix":7},"sk":{"a":0,"k":0,"ix":4},"sa":{"a":0,"k":0,"ix":5},"nm":"变换"}],"nm":"组 17","np":2,"cix":2,"ix":18,"mn":"ADBE Vector Group","hd":false},{"ty":"gr","it":[{"ind":0,"ty":"sh","ix":1,"ks":{"a":0,"k":{"i":[[-1.068,0.884],[-16.674,6.125],[-17.471,5.977],[-11.517,3.26],[0,0],[3.658,-1.158],[16.481,-6.088],[19.358,-8.174],[4.707,-1.54],[0.851,1.136]],"o":[[16.701,-6.068],[17.321,-6.362],[11.297,-3.865],[0,0],[-2.931,2.882],[-16.779,5.313],[-19.685,7.271],[-4.544,1.919],[-1.248,0.409],[-0.169,-1.076]],"v":[[-67.361,22.571],[-17.306,4.24],[34.701,-14.799],[68.429,-26.87],[68.429,-23.78],[57.899,-18.667],[8.354,-0.587],[-50.553,21.715],[-64.627,26.461],[-67.836,25.645]],"c":true},"ix":2},"nm":"路径 1","mn":"ADBE Vector Shape - Group","hd":false},{"ty":"fl","c":{"a":0,"k":[0.995999983245,0.658999992819,0,1],"ix":4},"o":{"a":0,"k":100,"ix":5},"r":1,"nm":"填充 1","mn":"ADBE Vector Graphic - Fill","hd":false},{"ty":"tr","p":{"a":0,"k":[86.778,98.314],"ix":2},"a":{"a":0,"k":[0,0],"ix":1},"s":{"a":0,"k":[100,100],"ix":3},"r":{"a":0,"k":0,"ix":6},"o":{"a":0,"k":100,"ix":7},"sk":{"a":0,"k":0,"ix":4},"sa":{"a":0,"k":0,"ix":5},"nm":"变换"}],"nm":"组 18","np":2,"cix":2,"ix":19,"mn":"ADBE Vector Group","hd":false},{"ty":"gr","it":[{"ind":0,"ty":"sh","ix":1,"ks":{"a":0,"k":{"i":[[0,0],[10.57,-3.932],[23.073,-8.543],[11.505,-4.353],[-0.965,1.03],[-21.796,8.142],[-16.221,5.375],[-8.252,-0.182]],"o":[[-11.053,2.497],[-23.06,8.579],[-11.536,4.271],[-0.965,-1.03],[21.794,-8.146],[16.018,-5.984],[7.402,-2.452],[0,0]],"v":[[68.378,-23.085],[36.367,-12.215],[-32.891,13.311],[-67.412,26.357],[-67.412,23.267],[-2.031,-1.171],[46.091,-18.921],[68.378,-26.175]],"c":true},"ix":2},"nm":"路径 1","mn":"ADBE Vector Shape - Group","hd":false},{"ty":"fl","c":{"a":0,"k":[0.995999983245,0.642999985639,0,1],"ix":4},"o":{"a":0,"k":100,"ix":5},"r":1,"nm":"填充 1","mn":"ADBE Vector Graphic - Fill","hd":false},{"ty":"tr","p":{"a":0,"k":[86.83,108.948],"ix":2},"a":{"a":0,"k":[0,0],"ix":1},"s":{"a":0,"k":[100,100],"ix":3},"r":{"a":0,"k":0,"ix":6},"o":{"a":0,"k":100,"ix":7},"sk":{"a":0,"k":0,"ix":4},"sa":{"a":0,"k":0,"ix":5},"nm":"变换"}],"nm":"组 19","np":2,"cix":2,"ix":20,"mn":"ADBE Vector Group","hd":false},{"ty":"gr","it":[{"ind":0,"ty":"sh","ix":1,"ks":{"a":0,"k":{"i":[[-1.73,-0.96],[0,0],[5.902,-2.07],[19.716,-7.087],[18.3,-6.494],[1.767,1.62],[-0.111,1.078],[-1.572,0.569],[-18.92,6.862],[-19.012,6.11],[-4.803,2.19]],"o":[[0,0],[-5.191,3.749],[-19.775,6.939],[-18.275,6.568],[-1.642,0.582],[-0.527,-1.03],[0.556,-2.005],[18.929,-6.851],[18.75,-6.799],[4.967,-1.596],[1.627,-0.741]],"v":[[68.322,-27.223],[68.322,-23.103],[51.161,-15.338],[-7.806,6.425],[-62.47,26.559],[-67.795,26.563],[-68.041,23.372],[-64.085,20.519],[-7.466,-0.479],[48.81,-20.843],[63.507,-26.714]],"c":true},"ix":2},"nm":"路径 1","mn":"ADBE Vector Shape - Group","hd":false},{"ty":"fl","c":{"a":0,"k":[0.995999983245,0.670999983245,0,1],"ix":4},"o":{"a":0,"k":100,"ix":5},"r":1,"nm":"填充 1","mn":"ADBE Vector Graphic - Fill","hd":false},{"ty":"tr","p":{"a":0,"k":[86.886,94.546],"ix":2},"a":{"a":0,"k":[0,0],"ix":1},"s":{"a":0,"k":[100,100],"ix":3},"r":{"a":0,"k":0,"ix":6},"o":{"a":0,"k":100,"ix":7},"sk":{"a":0,"k":0,"ix":4},"sa":{"a":0,"k":0,"ix":5},"nm":"变换"}],"nm":"组 20","np":2,"cix":2,"ix":21,"mn":"ADBE Vector Group","hd":false},{"ty":"gr","it":[{"ind":0,"ty":"sh","ix":1,"ks":{"a":0,"k":{"i":[[-3.266,-2.832],[0,0],[12.355,-4.561],[15.211,-5.724],[12.849,-4.677],[4.488,-0.09],[0.845,0.799],[-0.135,1.07],[-2.261,0.952],[-12.606,4.802],[-12.588,4.825],[-13.405,4.587],[-1.26,2.169]],"o":[[0,0],[-12.228,4.902],[-15.246,5.629],[-12.797,4.815],[-3.985,1.451],[-1.051,0.021],[-0.499,-1.027],[1.229,-2.924],[12.45,-5.243],[12.597,-4.8],[13.227,-5.069],[2.393,-0.818],[2.773,-0.944]],"v":[[68.316,-26.381],[68.316,-20.201],[31.298,-6.396],[-14.336,10.775],[-52.889,24.792],[-64.947,28.967],[-67.817,28.413],[-68.034,25.244],[-61.499,21.779],[-23.498,7.811],[14.365,-6.396],[54.248,-21.07],[59.768,-25.26]],"c":true},"ix":2},"nm":"路径 1","mn":"ADBE Vector Shape - Group","hd":false},{"ty":"fl","c":{"a":0,"k":[0.995999983245,0.725,0,1],"ix":4},"o":{"a":0,"k":100,"ix":5},"r":1,"nm":"填充 1","mn":"ADBE Vector Graphic - Fill","hd":false},{"ty":"tr","p":{"a":0,"k":[86.892,55.593],"ix":2},"a":{"a":0,"k":[0,0],"ix":1},"s":{"a":0,"k":[100,100],"ix":3},"r":{"a":0,"k":0,"ix":6},"o":{"a":0,"k":100,"ix":7},"sk":{"a":0,"k":0,"ix":4},"sa":{"a":0,"k":0,"ix":5},"nm":"变换"}],"nm":"组 21","np":2,"cix":2,"ix":22,"mn":"ADBE Vector Group","hd":false},{"ty":"gr","it":[{"ind":0,"ty":"sh","ix":1,"ks":{"a":0,"k":{"i":[[-1.062,1.717],[-10.265,3.648],[-15.18,5.581],[-0.887,1.54],[0,0],[4.522,-1.731],[27.313,-9.398]],"o":[[10.584,-2.748],[15.239,-5.416],[1.722,-0.632],[0,0],[-3.435,4.196],[-26.97,10.322],[-1.062,-1.717]],"v":[[-46.764,12.875],[-15.974,1.911],[29.527,-14.941],[33.405,-18.025],[47.826,-18.025],[34.506,-11.984],[-46.764,18.025]],"c":true},"ix":2},"nm":"路径 1","mn":"ADBE Vector Shape - Group","hd":false},{"ty":"fl","c":{"a":0,"k":[0.995999983245,0.783999992819,0,1],"ix":4},"o":{"a":0,"k":100,"ix":5},"r":1,"nm":"填充 1","mn":"ADBE Vector Graphic - Fill","hd":false},{"ty":"tr","p":{"a":0,"k":[66.181,28.698],"ix":2},"a":{"a":0,"k":[0,0],"ix":1},"s":{"a":0,"k":[100,100],"ix":3},"r":{"a":0,"k":0,"ix":6},"o":{"a":0,"k":100,"ix":7},"sk":{"a":0,"k":0,"ix":4},"sa":{"a":0,"k":0,"ix":5},"nm":"变换"}],"nm":"组 22","np":2,"cix":2,"ix":23,"mn":"ADBE Vector Group","hd":false},{"ty":"gr","it":[{"ind":0,"ty":"sh","ix":1,"ks":{"a":0,"k":{"i":[[-3.179,1.897],[0,0],[2.53,-1.033],[18.65,-7.089],[4.156,-1.541],[2.386,2.638],[-0.012,1.916],[-2.366,0.877],[-15.728,6.333]],"o":[[0,0],[0.735,3.739],[-18.478,7.547],[-4.143,1.574],[-2.495,0.925],[-0.389,-1.905],[1.125,-2.257],[15.892,-5.892],[3.342,-1.345]],"v":[[22.641,-16.76],[40.15,-16.76],[35.538,-11.213],[-20.51,9.792],[-32.949,14.494],[-40.497,14.122],[-40.654,8.377],[-35.372,3.81],[12.318,-13.828]],"c":true},"ix":2},"nm":"路径 1","mn":"ADBE Vector Shape - Group","hd":false},{"ty":"fl","c":{"a":0,"k":[0.995999983245,0.791999966491,0,1],"ix":4},"o":{"a":0,"k":100,"ix":5},"r":1,"nm":"填充 1","mn":"ADBE Vector Graphic - Fill","hd":false},{"ty":"tr","p":{"a":0,"k":[59.436,27.433],"ix":2},"a":{"a":0,"k":[0,0],"ix":1},"s":{"a":0,"k":[100,100],"ix":3},"r":{"a":0,"k":0,"ix":6},"o":{"a":0,"k":100,"ix":7},"sk":{"a":0,"k":0,"ix":4},"sa":{"a":0,"k":0,"ix":5},"nm":"变换"}],"nm":"组 23","np":2,"cix":2,"ix":24,"mn":"ADBE Vector Group","hd":false},{"ty":"gr","it":[{"ind":0,"ty":"sh","ix":1,"ks":{"a":0,"k":{"i":[[0,0],[9.613,-3.489],[18.992,-6.762],[17.052,-5.123],[0.052,1.328],[-1.339,0.401],[-11.934,4.469],[-16.389,6.704],[-13.194,5.631],[-2.523,-1.763]],"o":[[-10.152,1.965],[-18.952,6.878],[-16.751,5.964],[-1.226,-1.156],[0.578,-1.374],[12.244,-3.661],[16.589,-6.21],[13.28,-5.432],[2.287,-0.976],[0,0]],"v":[[68.508,-21.779],[39.578,-11.546],[-17.108,9.555],[-67.282,27.662],[-67.863,23.737],[-64.813,21.174],[-28.782,8.225],[21.016,-10.315],[61.244,-25.493],[68.508,-25.899]],"c":true},"ix":2},"nm":"路径 1","mn":"ADBE Vector Shape - Group","hd":false},{"ty":"fl","c":{"a":0,"k":[0.995999983245,0.717999985639,0,1],"ix":4},"o":{"a":0,"k":100,"ix":5},"r":1,"nm":"填充 1","mn":"ADBE Vector Graphic - Fill","hd":false},{"ty":"tr","p":{"a":0,"k":[86.7,63.352],"ix":2},"a":{"a":0,"k":[0,0],"ix":1},"s":{"a":0,"k":[100,100],"ix":3},"r":{"a":0,"k":0,"ix":6},"o":{"a":0,"k":100,"ix":7},"sk":{"a":0,"k":0,"ix":4},"sa":{"a":0,"k":0,"ix":5},"nm":"变换"}],"nm":"组 24","np":2,"cix":2,"ix":25,"mn":"ADBE Vector Group","hd":false},{"ty":"gr","it":[{"ind":0,"ty":"sh","ix":1,"ks":{"a":0,"k":{"i":[[0,0],[11.752,-4.191],[20.062,-7.46],[10.885,-4.124],[2.607,1.048],[-0.229,0.808],[-2.919,1.047],[-20.958,7.609],[-14.233,5.731],[-5.398,2.147],[-1.738,-1.926]],"o":[[-12.321,2.543],[-20.16,7.188],[-10.91,4.057],[-2.459,0.932],[-0.826,-0.591],[1.973,-3.013],[20.986,-7.531],[14.408,-5.232],[5.375,-2.165],[1.927,-0.766],[0,0]],"v":[[68.308,-21.192],[32.892,-9.034],[-27.327,13.26],[-60.04,25.477],[-67.482,26.19],[-67.932,23.999],[-59.533,19.534],[3.177,-3.73],[46.261,-19.878],[62.631,-25.804],[68.308,-25.312]],"c":true},"ix":2},"nm":"路径 1","mn":"ADBE Vector Shape - Group","hd":false},{"ty":"fl","c":{"a":0,"k":[0.995999983245,0.638999968884,0,1],"ix":4},"o":{"a":0,"k":100,"ix":5},"r":1,"nm":"填充 1","mn":"ADBE Vector Graphic - Fill","hd":false},{"ty":"tr","p":{"a":0,"k":[86.9,111.175],"ix":2},"a":{"a":0,"k":[0,0],"ix":1},"s":{"a":0,"k":[100,100],"ix":3},"r":{"a":0,"k":0,"ix":6},"o":{"a":0,"k":100,"ix":7},"sk":{"a":0,"k":0,"ix":4},"sa":{"a":0,"k":0,"ix":5},"nm":"变换"}],"nm":"组 25","np":2,"cix":2,"ix":26,"mn":"ADBE Vector Group","hd":false},{"ty":"gr","it":[{"ind":0,"ty":"sh","ix":1,"ks":{"a":0,"k":{"i":[[0,0],[17.594,-6.682],[11.396,-4.185],[14.524,-5.529],[1.74,0.051],[-1.032,1.373],[-10.709,3.987],[-15.077,5.543],[-10.924,3.996],[-8.518,3.055]],"o":[[-17.877,5.908],[-11.332,4.305],[-14.588,5.357],[-1.639,0.624],[-1.032,-1.373],[10.991,-3.2],[15.054,-5.605],[10.917,-4.014],[8.498,-3.109],[0,0]],"v":[[68.411,-22.686],[15.445,-3.173],[-18.764,9.32],[-62.396,25.747],[-67.379,26.755],[-67.379,22.635],[-35.111,11.072],[10.132,-5.523],[42.861,-17.629],[68.411,-26.806]],"c":true},"ix":2},"nm":"路径 1","mn":"ADBE Vector Shape - Group","hd":false},{"ty":"fl","c":{"a":0,"k":[0.995999983245,0.702000038297,0,1],"ix":4},"o":{"a":0,"k":100,"ix":5},"r":1,"nm":"填充 1","mn":"ADBE Vector Graphic - Fill","hd":false},{"ty":"tr","p":{"a":0,"k":[86.797,73.529],"ix":2},"a":{"a":0,"k":[0,0],"ix":1},"s":{"a":0,"k":[100,100],"ix":3},"r":{"a":0,"k":0,"ix":6},"o":{"a":0,"k":100,"ix":7},"sk":{"a":0,"k":0,"ix":4},"sa":{"a":0,"k":0,"ix":5},"nm":"变换"}],"nm":"组 26","np":2,"cix":2,"ix":27,"mn":"ADBE Vector Group","hd":false},{"ty":"gr","it":[{"ind":0,"ty":"sh","ix":1,"ks":{"a":0,"k":{"i":[[0,0],[14.571,-5.354],[17.124,-6.359],[13.548,-5.164],[-1.063,1.717],[-8.705,3.034],[-17.016,6.349],[-15.568,5.817],[-4.274,-0.315]],"o":[[-14.555,5.398],[-17.147,6.301],[-13.592,5.047],[-1.062,-1.717],[9.19,-1.634],[17.147,-5.975],[15.572,-5.809],[3.842,-1.436],[0,0]],"v":[[68.426,-23.533],[24.76,-7.347],[-26.711,11.471],[-67.363,26.938],[-67.363,21.788],[-41.266,12.632],[9.848,-6.234],[56.533,-23.735],[68.426,-26.623]],"c":true},"ix":2},"nm":"路径 1","mn":"ADBE Vector Shape - Group","hd":false},{"ty":"fl","c":{"a":0,"k":[0.995999983245,0.681999954523,0,1],"ix":4},"o":{"a":0,"k":100,"ix":5},"r":1,"nm":"填充 1","mn":"ADBE Vector Graphic - Fill","hd":false},{"ty":"tr","p":{"a":0,"k":[86.781,83.646],"ix":2},"a":{"a":0,"k":[0,0],"ix":1},"s":{"a":0,"k":[100,100],"ix":3},"r":{"a":0,"k":0,"ix":6},"o":{"a":0,"k":100,"ix":7},"sk":{"a":0,"k":0,"ix":4},"sa":{"a":0,"k":0,"ix":5},"nm":"变换"}],"nm":"组 27","np":2,"cix":2,"ix":28,"mn":"ADBE Vector Group","hd":false},{"ty":"gr","it":[{"ind":0,"ty":"sh","ix":1,"ks":{"a":0,"k":{"i":[[-2.366,-2.079],[0,0],[4.227,-0.037],[12.79,0.009],[-0.674,1.392],[-1.925,0.657],[-13.674,4.368]],"o":[[0,0],[-4.19,1.145],[-12.798,0.113],[-2.235,-0.041],[0.966,-1.996],[13.577,-4.637],[2.428,-0.776]],"v":[[26.657,-9.833],[26.657,10.767],[13.967,11.24],[-24.422,11.278],[-25.74,8.533],[-20.963,4.876],[19.403,-10.016]],"c":true},"ix":2},"nm":"路径 1","mn":"ADBE Vector Shape - Group","hd":false},{"ty":"fl","c":{"a":0,"k":[0.995999983245,0.573000021542,0,1],"ix":4},"o":{"a":0,"k":100,"ix":5},"r":1,"nm":"填充 1","mn":"ADBE Vector Graphic - Fill","hd":false},{"ty":"tr","p":{"a":0,"k":[128.551,135.867],"ix":2},"a":{"a":0,"k":[0,0],"ix":1},"s":{"a":0,"k":[100,100],"ix":3},"r":{"a":0,"k":0,"ix":6},"o":{"a":0,"k":100,"ix":7},"sk":{"a":0,"k":0,"ix":4},"sa":{"a":0,"k":0,"ix":5},"nm":"变换"}],"nm":"组 28","np":2,"cix":2,"ix":29,"mn":"ADBE Vector Group","hd":false},{"ty":"gr","it":[{"ind":0,"ty":"sh","ix":1,"ks":{"a":0,"k":{"i":[[-2.256,-2.102],[0,0],[6.795,-2.483],[9.766,-3.551],[12.624,-5.166],[12.902,-5.45],[3.401,2.006],[-0.072,1.355],[-1.888,0.734],[-14.565,5.381],[-27.293,10.415]],"o":[[0,0],[-5.963,4.549],[-9.755,3.565],[-12.818,4.661],[-12.954,5.302],[-2.777,1.173],[-0.468,-1.329],[0.596,-1.997],[14.474,-5.622],[27.401,-10.123],[2.181,-0.833]],"v":[[68.329,-27.312],[68.329,-22.162],[48.239,-13.541],[18.956,-2.848],[-19.413,11.362],[-58.732,26.022],[-67.861,27.408],[-68.06,23.362],[-64.113,19.715],[-20.504,3.355],[61.618,-27.24]],"c":true},"ix":2},"nm":"路径 1","mn":"ADBE Vector Shape - Group","hd":false},{"ty":"fl","c":{"a":0,"k":[0.995999983245,0.677999997606,0,1],"ix":4},"o":{"a":0,"k":100,"ix":5},"r":1,"nm":"填充 1","mn":"ADBE Vector Graphic - Fill","hd":false},{"ty":"tr","p":{"a":0,"k":[86.878,87.425],"ix":2},"a":{"a":0,"k":[0,0],"ix":1},"s":{"a":0,"k":[100,100],"ix":3},"r":{"a":0,"k":0,"ix":6},"o":{"a":0,"k":100,"ix":7},"sk":{"a":0,"k":0,"ix":4},"sa":{"a":0,"k":0,"ix":5},"nm":"变换"}],"nm":"组 29","np":2,"cix":2,"ix":30,"mn":"ADBE Vector Group","hd":false},{"ty":"gr","it":[{"ind":0,"ty":"sh","ix":1,"ks":{"a":0,"k":{"i":[[-1.886,-1.937],[0,0],[4.927,-1.618],[10.099,-3.597],[19.061,-6.901],[9.434,-3.523],[2.216,1.703],[-0.145,1.637],[-3.691,1.236],[-13.002,4.712],[-14.944,5.816],[-12.041,4.239]],"o":[[0,0],[-4.495,2.867],[-10.203,3.352],[-19.094,6.8],[-9.449,3.421],[-2.04,0.761],[-0.329,-1.63],[2.35,-4.177],[13.131,-4.394],[15.076,-5.462],[11.903,-4.633],[1.933,-0.681]],"v":[[68.304,-27.135],[68.304,-21.984],[53.77,-15.82],[23.554,-4.781],[-33.562,16.095],[-61.772,26.887],[-67.975,27.368],[-68.057,22.464],[-57.338,17.135],[-18.498,2.548],[26.624,-14.139],[62.639,-27.152]],"c":true},"ix":2},"nm":"路径 1","mn":"ADBE Vector Shape - Group","hd":false},{"ty":"fl","c":{"a":0,"k":[0.995999983245,0.651000019148,0,1],"ix":4},"o":{"a":0,"k":100,"ix":5},"r":1,"nm":"填充 1","mn":"ADBE Vector Graphic - Fill","hd":false},{"ty":"tr","p":{"a":0,"k":[86.904,104.758],"ix":2},"a":{"a":0,"k":[0,0],"ix":1},"s":{"a":0,"k":[100,100],"ix":3},"r":{"a":0,"k":0,"ix":6},"o":{"a":0,"k":100,"ix":7},"sk":{"a":0,"k":0,"ix":4},"sa":{"a":0,"k":0,"ix":5},"nm":"变换"}],"nm":"组 30","np":2,"cix":2,"ix":31,"mn":"ADBE Vector Group","hd":false},{"ty":"gr","it":[{"ind":0,"ty":"sh","ix":1,"ks":{"a":0,"k":{"i":[[4.047,1.49],[-5.372,2.033],[-20.396,7.564],[-15.577,5.801],[-3.727,-0.13],[0,0],[2.182,-0.749],[9.622,-3.426],[19.35,-7.056],[9.904,-3.558]],"o":[[4.273,-4.414],[20.343,-7.703],[15.585,-5.78],[3.355,-1.249],[0,0],[-1.266,1.973],[-9.659,3.312],[-19.404,6.909],[-9.882,3.603],[-4.114,-0.374]],"v":[[-66.951,24.469],[-51.342,16.993],[9.878,-5.612],[56.563,-23.137],[66.951,-25.829],[66.951,-21.71],[61.611,-18.049],[32.868,-7.458],[-25.102,13.931],[-54.596,25.147]],"c":true},"ix":2},"nm":"路径 1","mn":"ADBE Vector Shape - Group","hd":false},{"ty":"fl","c":{"a":0,"k":[0.995999983245,0.620000023935,0,1],"ix":4},"o":{"a":0,"k":100,"ix":5},"r":1,"nm":"填充 1","mn":"ADBE Vector Graphic - Fill","hd":false},{"ty":"tr","p":{"a":0,"k":[88.257,121.993],"ix":2},"a":{"a":0,"k":[0,0],"ix":1},"s":{"a":0,"k":[100,100],"ix":3},"r":{"a":0,"k":0,"ix":6},"o":{"a":0,"k":100,"ix":7},"sk":{"a":0,"k":0,"ix":4},"sa":{"a":0,"k":0,"ix":5},"nm":"变换"}],"nm":"组 31","np":2,"cix":2,"ix":32,"mn":"ADBE Vector Group","hd":false},{"ty":"gr","it":[{"ind":0,"ty":"sh","ix":1,"ks":{"a":0,"k":{"i":[[-2.674,-2.386],[0,0],[7.978,-2.932],[26.498,-9.594],[8.947,-3.836],[1.747,2.216],[-0.12,1.645],[-5.174,2.066],[-17.416,6.463],[-20.499,7.482]],"o":[[0,0],[-7.458,4.26],[-26.45,9.721],[-9.136,3.308],[-2.196,0.942],[-0.349,-1.635],[4.235,-4.052],[17.259,-6.891],[20.458,-7.591],[2.421,-0.883]],"v":[[68.31,-27.208],[68.31,-21.027],[44.628,-11.462],[-34.663,17.859],[-61.971,28.148],[-67.961,27.378],[-68.064,22.452],[-52.982,15.382],[-0.743,-4.044],[60.631,-26.826]],"c":true},"ix":2},"nm":"路径 1","mn":"ADBE Vector Shape - Group","hd":false},{"ty":"fl","c":{"a":0,"k":[0.995999983245,0.689999988032,0,1],"ix":4},"o":{"a":0,"k":100,"ix":5},"r":1,"nm":"填充 1","mn":"ADBE Vector Graphic - Fill","hd":false},{"ty":"tr","p":{"a":0,"k":[86.898,78.051],"ix":2},"a":{"a":0,"k":[0,0],"ix":1},"s":{"a":0,"k":[100,100],"ix":3},"r":{"a":0,"k":0,"ix":6},"o":{"a":0,"k":100,"ix":7},"sk":{"a":0,"k":0,"ix":4},"sa":{"a":0,"k":0,"ix":5},"nm":"变换"}],"nm":"组 32","np":2,"cix":2,"ix":33,"mn":"ADBE Vector Group","hd":false},{"ty":"gr","it":[{"ind":0,"ty":"sh","ix":1,"ks":{"a":0,"k":{"i":[[-2.134,-2.177],[0,0],[4.313,-1.64],[13.876,-4.764],[15.735,-5.19],[9.933,-3.654],[1.875,2.155],[-0.089,1.641],[-1.697,0.606],[-27.364,10.271],[-14.537,5.517]],"o":[[0,0],[-2.997,4.397],[-13.729,5.221],[-15.659,5.377],[-10.012,3.303],[-2.16,0.794],[-0.375,-1.629],[0.781,-1.641],[27.528,-9.823],[14.555,-5.463],[2.265,-0.859]],"v":[[68.317,-27.288],[68.317,-22.137],[55.788,-15.764],[14.508,-0.352],[-32.171,16.574],[-61.863,27.783],[-67.942,27.309],[-68.07,22.396],[-64.285,19.15],[17.952,-11.257],[61.651,-27.568]],"c":true},"ix":2},"nm":"路径 1","mn":"ADBE Vector Shape - Group","hd":false},{"ty":"fl","c":{"a":0,"k":[0.995999983245,0.705999995213,0,1],"ix":4},"o":{"a":0,"k":100,"ix":5},"r":1,"nm":"填充 1","mn":"ADBE Vector Graphic - Fill","hd":false},{"ty":"tr","p":{"a":0,"k":[86.891,68.861],"ix":2},"a":{"a":0,"k":[0,0],"ix":1},"s":{"a":0,"k":[100,100],"ix":3},"r":{"a":0,"k":0,"ix":6},"o":{"a":0,"k":100,"ix":7},"sk":{"a":0,"k":0,"ix":4},"sa":{"a":0,"k":0,"ix":5},"nm":"变换"}],"nm":"组 33","np":2,"cix":2,"ix":34,"mn":"ADBE Vector Group","hd":false},{"ty":"gr","it":[{"ind":0,"ty":"sh","ix":1,"ks":{"a":0,"k":{"i":[[-1.912,-2.017],[0,0],[4.415,-1.646],[19.546,-7.318],[21.178,-7.356],[0.886,2.996],[-3.673,1.416],[-18.428,6.786],[-21.572,7.173]],"o":[[0,0],[-3.424,3.835],[-19.56,7.288],[-20.991,7.86],[-3.781,-2.46],[3.056,-2.969],[18.324,-7.062],[21.323,-7.851],[2.153,-0.716]],"v":[[69.253,-27.553],[69.253,-21.373],[56.387,-15.311],[-2.341,6.428],[-65.472,29.57],[-67.184,20.402],[-56.154,15.98],[-0.964,-4.643],[63.059,-28.066]],"c":true},"ix":2},"nm":"路径 1","mn":"ADBE Vector Shape - Group","hd":false},{"ty":"fl","c":{"a":0,"k":[0.995999983245,0.630999995213,0,1],"ix":4},"o":{"a":0,"k":100,"ix":5},"r":1,"nm":"填充 1","mn":"ADBE Vector Graphic - Fill","hd":false},{"ty":"tr","p":{"a":0,"k":[85.955,117.537],"ix":2},"a":{"a":0,"k":[0,0],"ix":1},"s":{"a":0,"k":[100,100],"ix":3},"r":{"a":0,"k":0,"ix":6},"o":{"a":0,"k":100,"ix":7},"sk":{"a":0,"k":0,"ix":4},"sa":{"a":0,"k":0,"ix":5},"nm":"变换"}],"nm":"组 34","np":2,"cix":2,"ix":35,"mn":"ADBE Vector Group","hd":false},{"ty":"gr","it":[{"ind":0,"ty":"sh","ix":1,"ks":{"a":0,"k":{"i":[[-1.39,2.14],[-14.929,5.404],[-23.165,8.793],[-7.082,2.514],[0,0],[6.182,-2.396],[8.47,-4.017],[8.037,-2.887],[19.767,-6.142],[1.579,-0.651],[1.21,2.326]],"o":[[15.243,-4.521],[23.299,-8.434],[7.03,-2.669],[0,0],[-5.381,4.277],[-8.739,3.387],[-7.789,3.695],[-19.462,6.992],[-1.695,0.527],[-1.853,0.765],[0.238,-2.252]],"v":[[-67.2,20.18],[-22.315,4.233],[47.425,-21.498],[68.59,-29.261],[68.59,-22.051],[50.295,-14.212],[23.916,-4.49],[-0.192,4.273],[-58.444,25.597],[-62.999,27.915],[-67.834,26.935]],"c":true},"ix":2},"nm":"路径 1","mn":"ADBE Vector Shape - Group","hd":false},{"ty":"fl","c":{"a":0,"k":[0.995999983245,0.741000007181,0,1],"ix":4},"o":{"a":0,"k":100,"ix":5},"r":1,"nm":"填充 1","mn":"ADBE Vector Graphic - Fill","hd":false},{"ty":"tr","p":{"a":0,"k":[86.617,45.084],"ix":2},"a":{"a":0,"k":[0,0],"ix":1},"s":{"a":0,"k":[100,100],"ix":3},"r":{"a":0,"k":0,"ix":6},"o":{"a":0,"k":100,"ix":7},"sk":{"a":0,"k":0,"ix":4},"sa":{"a":0,"k":0,"ix":5},"nm":"变换"}],"nm":"组 35","np":2,"cix":2,"ix":36,"mn":"ADBE Vector Group","hd":false},{"ty":"gr","it":[{"ind":0,"ty":"sh","ix":1,"ks":{"a":0,"k":{"i":[[0,0],[1.895,-0.704],[34.882,-12.918],[2.302,-0.667],[0.304,2.504],[-3.92,1.473],[-23.344,9.229],[-4.304,2.272]],"o":[[-0.578,2.498],[-34.871,12.947],[-2.242,0.83],[-1.437,-2.408],[1.918,-5.045],[23.495,-8.83],[4.506,-1.782],[0,0]],"v":[[58.829,-22.146],[54.128,-18.699],[-50.493,20.123],[-57.392,22.146],[-58.054,14.604],[-47.082,8.03],[23.424,-18.411],[37.199,-22.146]],"c":true},"ix":2},"nm":"路径 1","mn":"ADBE Vector Shape - Group","hd":false},{"ty":"fl","c":{"a":0,"k":[0.995999983245,0.776000019148,0,1],"ix":4},"o":{"a":0,"k":100,"ix":5},"r":1,"nm":"填充 1","mn":"ADBE Vector Graphic - Fill","hd":false},{"ty":"tr","p":{"a":0,"k":[76.809,32.818],"ix":2},"a":{"a":0,"k":[0,0],"ix":1},"s":{"a":0,"k":[100,100],"ix":3},"r":{"a":0,"k":0,"ix":6},"o":{"a":0,"k":100,"ix":7},"sk":{"a":0,"k":0,"ix":4},"sa":{"a":0,"k":0,"ix":5},"nm":"变换"}],"nm":"组 36","np":2,"cix":2,"ix":37,"mn":"ADBE Vector Group","hd":false},{"ty":"gr","it":[{"ind":0,"ty":"sh","ix":1,"ks":{"a":0,"k":{"i":[[-3.154,2.411],[-4.761,0.465],[0.925,-4.358],[2.3,-0.808],[20.088,-7.42],[18.237,-7.01],[3.583,-1.16],[1.188,2.092],[-0.018,3.094],[-2.159,0.796],[-15.499,5.856],[-18.275,6.732]],"o":[[4.807,0],[4.406,-0.431],[-1.048,2.434],[-20.209,7.097],[-18.324,6.768],[-3.532,1.357],[-1.84,0.596],[-0.149,-3.098],[0.701,-2.438],[15.55,-5.728],[18.219,-6.884],[3.534,-1.302]],"v":[[48.242,-27.903],[62.652,-28.008],[67.812,-22.753],[62.315,-18.462],[2.015,3.722],[-52.885,24.251],[-63.632,27.757],[-68.588,26.347],[-68.637,17.057],[-63.808,12.947],[-17.193,-4.332],[37.533,-24.786]],"c":true},"ix":2},"nm":"路径 1","mn":"ADBE Vector Shape - Group","hd":false},{"ty":"fl","c":{"a":0,"k":[0.995999983245,0.757000014361,0,1],"ix":4},"o":{"a":0,"k":100,"ix":5},"r":1,"nm":"填充 1","mn":"ADBE Vector Graphic - Fill","hd":false},{"ty":"tr","p":{"a":0,"k":[87.395,38.575],"ix":2},"a":{"a":0,"k":[0,0],"ix":1},"s":{"a":0,"k":[100,100],"ix":3},"r":{"a":0,"k":0,"ix":6},"o":{"a":0,"k":100,"ix":7},"sk":{"a":0,"k":0,"ix":4},"sa":{"a":0,"k":0,"ix":5},"nm":"变换"}],"nm":"组 37","np":2,"cix":2,"ix":38,"mn":"ADBE Vector Group","hd":false}],"ip":0,"op":6001,"st":0,"bm":0}]}],"layers":[{"ddd":0,"ind":1,"ty":0,"nm":"预合成 1","refId":"comp_0","sr":1,"ks":{"o":{"a":1,"k":[{"i":{"x":[0.833],"y":[0.833]},"o":{"x":[0.167],"y":[0.167]},"n":["0p833_0p833_0p167_0p167"],"t":121,"s":[0],"e":[100]},{"t":123}],"ix":11},"r":{"a":0,"k":0,"ix":10},"p":{"a":0,"k":[360,640,0],"ix":2},"a":{"a":0,"k":[360,640,0],"ix":1},"s":{"a":0,"k":[108,108,100],"ix":6}},"ao":0,"w":720,"h":1280,"ip":0,"op":6001,"st":0,"bm":0},{"ddd":0,"ind":2,"ty":4,"nm":"形状图层 1","sr":1,"ks":{"o":{"a":1,"k":[{"i":{"x":[0.833],"y":[0.833]},"o":{"x":[0.167],"y":[0.167]},"n":["0p833_0p833_0p167_0p167"],"t":107,"s":[0],"e":[100]},{"t":123}],"ix":11},"r":{"a":0,"k":0,"ix":10},"p":{"a":0,"k":[358,639.705,0],"ix":2},"a":{"a":0,"k":[28.898,42.945,0],"ix":1},"s":{"a":1,"k":[{"i":{"x":[0.833,0.833,0.833],"y":[0.879,0.879,-153.303]},"o":{"x":[0.87,0.87,0.87],"y":[0,0,0]},"n":["0p833_0p879_0p87_0","0p833_0p879_0p87_0","0p833_-153p303_0p87_0"],"t":107,"s":[0,0,100],"e":[1273,1273,100]},{"t":123}],"ix":6}},"ao":0,"shapes":[{"ty":"gr","it":[{"d":1,"ty":"el","s":{"a":0,"k":[117.055,117.055],"ix":2},"p":{"a":0,"k":[0,0],"ix":3},"nm":"椭圆路径 1","mn":"ADBE Vector Shape - Ellipse","hd":false},{"ty":"fl","c":{"a":0,"k":[1,1,1,1],"ix":4},"o":{"a":0,"k":100,"ix":5},"r":1,"nm":"填充 1","mn":"ADBE Vector Graphic - Fill","hd":false},{"ty":"tr","p":{"a":0,"k":[28.898,42.945],"ix":2},"a":{"a":0,"k":[0,0],"ix":1},"s":{"a":0,"k":[100,100],"ix":3},"r":{"a":0,"k":0,"ix":6},"o":{"a":0,"k":100,"ix":7},"sk":{"a":0,"k":0,"ix":4},"sa":{"a":0,"k":0,"ix":5},"nm":"变换"}],"nm":"椭圆 1","np":3,"cix":2,"ix":1,"mn":"ADBE Vector Group","hd":false}],"ip":0,"op":6001,"st":0,"bm":0},{"ddd":0,"ind":3,"ty":4,"nm":"“Discover & Share interests”轮廓","sr":1,"ks":{"o":{"a":1,"k":[{"i":{"x":[0.833],"y":[0.9]},"o":{"x":[0.47],"y":[0]},"n":["0p833_0p9_0p47_0"],"t":40,"s":[0],"e":[100]},{"t":46}],"ix":11},"r":{"a":0,"k":0,"ix":10},"p":{"a":1,"k":[{"i":{"x":0.11,"y":1},"o":{"x":0.167,"y":0.049},"n":"0p11_1_0p167_0p049","t":40,"s":[529.115,640,0],"e":[486.115,640,0],"to":[-7.16666650772095,0,0],"ti":[7.16666650772095,0,0]},{"i":{"x":0.11,"y":0.11},"o":{"x":0.167,"y":0.167},"n":"0p11_0p11_0p167_0p167","t":46,"s":[486.115,640,0],"e":[486.115,640,0],"to":[0,0,0],"ti":[0,0,0]},{"i":{"x":0.11,"y":1},"o":{"x":0.167,"y":0.071},"n":"0p11_1_0p167_0p071","t":65,"s":[486.115,640,0],"e":[486.115,592.5,0],"to":[0,-7.91666650772095,0],"ti":[0,7.91666650772095,0]},{"i":{"x":0.11,"y":0.11},"o":{"x":0.167,"y":0.167},"n":"0p11_0p11_0p167_0p167","t":76,"s":[486.115,592.5,0],"e":[486.115,592.5,0],"to":[0,0,0],"ti":[0,0,0]},{"i":{"x":0.11,"y":1},"o":{"x":0.167,"y":0.063},"n":"0p11_1_0p167_0p063","t":91,"s":[486.115,592.5,0],"e":[419.115,592.5,0],"to":[-11.1666631698608,0,0],"ti":[11.1666631698608,0,0]},{"t":100}],"ix":2},"a":{"a":0,"k":[94.536,-7.465,0],"ix":1},"s":{"a":0,"k":[306.55,306.55,100],"ix":6}},"ao":0,"shapes":[{"ty":"gr","it":[{"ind":0,"ty":"sh","ix":1,"ks":{"a":0,"k":{"i":[[-0.226,-0.519],[-0.42,-0.373],[-0.605,-0.208],[-0.752,0],[-0.622,0.178],[-0.561,0.369],[0,0],[0,0],[0,0],[-0.209,0.793],[0,0.916],[0,0],[0.106,-0.437],[0.191,-0.376],[0,0],[0,0],[-0.243,0.239],[-0.178,0.273],[-0.099,0.308],[0,0.349],[0.178,0.42],[0.331,0.318],[0.472,0.185],[0.581,0],[0.502,-0.188],[0.352,-0.345],[0.195,-0.482],[0,-0.588],[-0.253,-0.523],[-0.444,-0.595],[0.331,-0.277],[0.236,-0.308],[0.133,-0.352],[0,-0.431]],"o":[[0.226,0.52],[0.42,0.373],[0.605,0.208],[0.725,0],[0.622,-0.178],[0,0],[0,0],[0,0],[0.478,-0.642],[0.208,-0.793],[0,0],[0,0.499],[-0.106,0.438],[0,0],[0,0],[0.294,-0.205],[0.243,-0.239],[0.178,-0.273],[0.099,-0.308],[0,-0.472],[-0.178,-0.42],[-0.332,-0.318],[-0.472,-0.185],[-0.615,0],[-0.502,0.188],[-0.352,0.345],[-0.195,0.482],[0,0.567],[0.253,0.523],[-0.403,0.28],[-0.332,0.277],[-0.236,0.308],[-0.133,0.352],[0,0.615]],"v":[[88.471,-2.317],[89.44,-0.979],[90.978,-0.108],[93.013,0.205],[95.033,-0.062],[96.807,-0.882],[97.576,0],[100.939,0],[98.704,-2.594],[99.735,-4.748],[100.047,-7.311],[97.525,-7.311],[97.366,-5.906],[96.92,-4.686],[94.346,-7.68],[95.3,-8.367],[96.105,-9.034],[96.735,-9.803],[97.151,-10.674],[97.299,-11.659],[97.033,-12.997],[96.269,-14.104],[95.064,-14.858],[93.485,-15.135],[91.808,-14.853],[90.527,-14.053],[89.706,-12.812],[89.414,-11.208],[89.793,-9.572],[90.839,-7.896],[89.737,-7.06],[88.886,-6.183],[88.332,-5.194],[88.132,-4.02]],"c":true},"ix":2},"nm":"&","mn":"ADBE Vector Shape - Group","hd":false},{"ind":1,"ty":"sh","ix":2,"ks":{"a":0,"k":{"i":[[0.253,0.099],[0.181,0.181],[0.096,0.246],[0,0.287],[-0.024,0.147],[-0.065,0.154],[-0.12,0.161],[-0.191,0.164],[0,0],[0,0],[0.711,0]],"o":[[-0.253,-0.099],[-0.181,-0.181],[-0.096,-0.246],[0,-0.137],[0.024,-0.147],[0.065,-0.154],[0.12,-0.161],[0,0],[0,0],[-0.636,0.397],[-0.308,0]],"v":[[92.316,-2.323],[91.665,-2.743],[91.25,-3.384],[91.106,-4.184],[91.142,-4.609],[91.275,-5.06],[91.552,-5.532],[92.019,-6.019],[92.234,-6.173],[95.177,-2.769],[93.157,-2.174]],"c":true},"ix":2},"nm":"&","mn":"ADBE Vector Shape - Group","hd":false},{"ind":2,"ty":"sh","ix":3,"ks":{"a":0,"k":{"i":[[-0.058,0.181],[-0.12,0.137],[-0.174,0.079],[-0.232,0],[-0.171,-0.075],[-0.113,-0.12],[-0.062,-0.15],[0,-0.157],[0.031,-0.137],[0.079,-0.133],[0.14,-0.13],[0.212,-0.137],[0,0],[0.164,0.314],[0,0.308]],"o":[[0.058,-0.181],[0.12,-0.137],[0.174,-0.079],[0.212,0],[0.171,0.075],[0.113,0.12],[0.062,0.15],[0,0.157],[-0.031,0.137],[-0.079,0.133],[-0.14,0.13],[0,0],[-0.273,-0.355],[-0.164,-0.314],[0,-0.205]],"v":[[92.157,-11.828],[92.424,-12.305],[92.865,-12.628],[93.475,-12.746],[94.049,-12.633],[94.474,-12.341],[94.736,-11.936],[94.828,-11.474],[94.782,-11.033],[94.618,-10.628],[94.29,-10.233],[93.762,-9.833],[92.972,-9.311],[92.316,-10.315],[92.07,-11.249]],"c":true},"ix":2},"nm":"&","mn":"ADBE Vector Shape - Group","hd":false},{"ty":"mm","mm":1,"nm":"合并路径 1","mn":"ADBE Vector Filter - Merge","hd":false},{"ty":"fl","c":{"a":0,"k":[1,1,1,1],"ix":4},"o":{"a":0,"k":100,"ix":5},"r":1,"nm":"填充 1","mn":"ADBE Vector Graphic - Fill","hd":false},{"ty":"tr","p":{"a":0,"k":[0,0],"ix":2},"a":{"a":0,"k":[0,0],"ix":1},"s":{"a":0,"k":[100,100],"ix":3},"r":{"a":0,"k":0,"ix":6},"o":{"a":0,"k":100,"ix":7},"sk":{"a":0,"k":0,"ix":4},"sa":{"a":0,"k":0,"ix":5},"nm":"变换"}],"nm":"&","np":6,"cix":2,"ix":1,"mn":"ADBE Vector Group","hd":false}],"ip":0,"op":6001,"st":0,"bm":0},{"ddd":0,"ind":4,"ty":4,"nm":"“Discover & ”轮廓","sr":1,"ks":{"o":{"a":1,"k":[{"i":{"x":[0.25],"y":[1]},"o":{"x":[0.167],"y":[0.167]},"n":["0p25_1_0p167_0p167"],"t":16,"s":[0],"e":[100]},{"t":26}],"ix":11},"r":{"a":0,"k":0,"ix":10},"p":{"a":1,"k":[{"i":{"x":0.833,"y":1},"o":{"x":0.167,"y":0.136},"n":"0p833_1_0p167_0p136","t":40,"s":[392,640,0],"e":[360,640,0],"to":[-5.33333349227905,0,0],"ti":[5.33333349227905,0,0]},{"i":{"x":0.833,"y":0.833},"o":{"x":0.167,"y":0.167},"n":"0p833_0p833_0p167_0p167","t":46,"s":[360,640,0],"e":[360,640,0],"to":[0,0,0],"ti":[0,0,0]},{"i":{"x":0.25,"y":1},"o":{"x":0.167,"y":0.167},"n":"0p25_1_0p167_0p167","t":65,"s":[360,640,0],"e":[360,592,0],"to":[0,-8,0],"ti":[0,8,0]},{"i":{"x":0.25,"y":0.25},"o":{"x":0.167,"y":0.167},"n":"0p25_0p25_0p167_0p167","t":76,"s":[360,592,0],"e":[360,592,0],"to":[0,0,0],"ti":[0,0,0]},{"i":{"x":0.25,"y":1},"o":{"x":0.167,"y":0.167},"n":"0p25_1_0p167_0p167","t":91,"s":[360,592,0],"e":[293,592,0],"to":[-11.1666669845581,0,0],"ti":[11.1666669845581,0,0]},{"t":100}],"ix":2},"a":{"a":0,"k":[51.136,-7.644,0],"ix":1},"s":{"a":1,"k":[{"i":{"x":[0.25,0.25,0.25],"y":[1,1,1]},"o":{"x":[0.167,0.167,0.167],"y":[0.167,0.167,-7.833]},"n":["0p25_1_0p167_0p167","0p25_1_0p167_0p167","0p25_1_0p167_-7p833"],"t":16,"s":[340.183,340.183,100],"e":[293.183,293.183,100]},{"t":26}],"ix":6}},"ao":0,"shapes":[{"ty":"gr","it":[{"ind":0,"ty":"sh","ix":1,"ks":{"a":0,"k":{"i":[[0,0],[-0.841,0.342],[-0.605,0.625],[-0.332,0.872],[0,1.066],[0,0],[0.335,0.875],[0.598,0.625],[0.837,0.345],[1.005,0],[0,0],[0,0]],"o":[[1.012,0],[0.841,-0.342],[0.605,-0.625],[0.331,-0.872],[0,0],[0,-1.066],[-0.335,-0.875],[-0.598,-0.625],[-0.837,-0.345],[0,0],[0,0],[0,0]],"v":[[5.896,0],[8.675,-0.513],[10.844,-1.964],[12.248,-4.209],[12.746,-7.116],[12.746,-7.793],[12.243,-10.705],[10.844,-12.956],[8.69,-14.412],[5.927,-14.93],[1.333,-14.93],[1.333,0]],"c":true},"ix":2},"nm":"D","mn":"ADBE Vector Shape - Group","hd":false},{"ind":1,"ty":"sh","ix":2,"ks":{"a":0,"k":{"i":[[0,0],[-0.629,-0.783],[0,-1.518],[0,0],[0.636,-0.803],[1.217,0],[0,0],[0,0]],"o":[[1.21,0],[0.629,0.783],[0,0],[0,1.49],[-0.636,0.803],[0,0],[0,0],[0,0]],"v":[[5.927,-12.438],[8.685,-11.264],[9.628,-7.813],[9.628,-7.116],[8.675,-3.676],[5.896,-2.471],[4.409,-2.471],[4.409,-12.438]],"c":true},"ix":2},"nm":"D","mn":"ADBE Vector Shape - Group","hd":false},{"ty":"mm","mm":1,"nm":"合并路径 1","mn":"ADBE Vector Filter - Merge","hd":false},{"ty":"fl","c":{"a":0,"k":[1,1,1,1],"ix":4},"o":{"a":0,"k":100,"ix":5},"r":1,"nm":"填充 1","mn":"ADBE Vector Graphic - Fill","hd":false},{"ty":"tr","p":{"a":0,"k":[0,0],"ix":2},"a":{"a":0,"k":[0,0],"ix":1},"s":{"a":0,"k":[100,100],"ix":3},"r":{"a":0,"k":0,"ix":6},"o":{"a":0,"k":100,"ix":7},"sk":{"a":0,"k":0,"ix":4},"sa":{"a":0,"k":0,"ix":5},"nm":"变换"}],"nm":"D","np":5,"cix":2,"ix":1,"mn":"ADBE Vector Group","hd":false},{"ty":"gr","it":[{"ind":0,"ty":"sh","ix":1,"ks":{"a":0,"k":{"i":[[0,0],[0,0],[0,0],[0,0]],"o":[[0,0],[0,0],[0,0],[0,0]],"v":[[17.914,-11.095],[14.94,-11.095],[14.94,0],[17.914,0]],"c":true},"ix":2},"nm":"i","mn":"ADBE Vector Shape - Group","hd":false},{"ind":1,"ty":"sh","ix":2,"ks":{"a":0,"k":{"i":[[-0.079,-0.188],[-0.144,-0.137],[-0.205,-0.075],[-0.253,0],[-0.205,0.075],[-0.144,0.137],[-0.079,0.188],[0,0.226],[0.079,0.188],[0.144,0.137],[0.205,0.075],[0.253,0],[0.297,-0.287],[0,-0.444]],"o":[[0.079,0.188],[0.144,0.137],[0.205,0.075],[0.253,0],[0.205,-0.075],[0.144,-0.137],[0.079,-0.188],[0,-0.219],[-0.079,-0.188],[-0.144,-0.137],[-0.205,-0.075],[-0.513,0],[-0.297,0.287],[0,0.226]],"v":[[14.884,-13.345],[15.217,-12.858],[15.74,-12.541],[16.427,-12.428],[17.114,-12.541],[17.637,-12.858],[17.97,-13.345],[18.088,-13.966],[17.97,-14.576],[17.637,-15.063],[17.114,-15.381],[16.427,-15.494],[15.212,-15.063],[14.766,-13.966]],"c":true},"ix":2},"nm":"i","mn":"ADBE Vector Shape - Group","hd":false},{"ty":"mm","mm":1,"nm":"合并路径 1","mn":"ADBE Vector Filter - Merge","hd":false},{"ty":"fl","c":{"a":0,"k":[1,1,1,1],"ix":4},"o":{"a":0,"k":100,"ix":5},"r":1,"nm":"填充 1","mn":"ADBE Vector Graphic - Fill","hd":false},{"ty":"tr","p":{"a":0,"k":[0,0],"ix":2},"a":{"a":0,"k":[0,0],"ix":1},"s":{"a":0,"k":[100,100],"ix":3},"r":{"a":0,"k":0,"ix":6},"o":{"a":0,"k":100,"ix":7},"sk":{"a":0,"k":0,"ix":4},"sa":{"a":0,"k":0,"ix":5},"nm":"变换"}],"nm":"i","np":5,"cix":2,"ix":2,"mn":"ADBE Vector Group","hd":false},{"ty":"gr","it":[{"ind":0,"ty":"sh","ix":1,"ks":{"a":0,"k":{"i":[[0.29,-0.215],[0.567,0],[0.243,0.062],[0.185,0.13],[0.113,0.209],[0.014,0.287],[0,0],[-0.205,-0.444],[-0.407,-0.355],[-0.595,-0.219],[-0.779,0],[-0.574,0.171],[-0.407,0.301],[-0.219,0.414],[0,0.492],[0.212,0.386],[0.373,0.27],[0.513,0.171],[0.601,0.116],[0.263,0.089],[0.161,0.106],[0.072,0.127],[0,0.164],[-0.273,0.226],[-0.499,0],[-0.273,-0.277],[0,-0.424],[0,0],[0.215,0.438],[0.4,0.318],[0.574,0.178],[0.718,0],[0.55,-0.185],[0.379,-0.318],[0.202,-0.417],[0,-0.465],[-0.198,-0.362],[-0.352,-0.273],[-0.482,-0.185],[-0.567,-0.123],[-0.294,-0.103],[-0.171,-0.113],[-0.062,-0.13],[0,-0.157]],"o":[[-0.291,0.215],[-0.267,0],[-0.243,-0.062],[-0.185,-0.13],[-0.113,-0.208],[0,0],[0,0.451],[0.205,0.444],[0.407,0.356],[0.595,0.219],[0.711,0],[0.574,-0.171],[0.407,-0.301],[0.219,-0.414],[0,-0.547],[-0.212,-0.386],[-0.373,-0.27],[-0.513,-0.171],[-0.383,-0.075],[-0.263,-0.089],[-0.161,-0.106],[-0.072,-0.126],[0,-0.349],[0.273,-0.226],[0.581,0],[0.273,0.277],[0,0],[0,-0.519],[-0.215,-0.437],[-0.4,-0.318],[-0.574,-0.178],[-0.691,0],[-0.55,0.185],[-0.379,0.318],[-0.202,0.417],[0,0.479],[0.198,0.362],[0.352,0.273],[0.482,0.185],[0.465,0.096],[0.294,0.103],[0.171,0.113],[0.062,0.13],[0,0.349]],"v":[[25.927,-2.22],[24.64,-1.897],[23.876,-1.989],[23.235,-2.276],[22.789,-2.784],[22.6,-3.527],[19.79,-3.527],[20.098,-2.184],[21.015,-0.984],[22.518,-0.123],[24.579,0.205],[26.506,-0.051],[27.978,-0.759],[28.916,-1.83],[29.244,-3.189],[28.926,-4.589],[28.05,-5.573],[26.722,-6.234],[25.05,-6.665],[24.081,-6.911],[23.446,-7.203],[23.097,-7.552],[22.989,-7.988],[23.399,-8.849],[24.558,-9.188],[25.84,-8.772],[26.25,-7.721],[29.213,-7.721],[28.89,-9.157],[27.968,-10.29],[26.506,-11.033],[24.568,-11.3],[22.707,-11.023],[21.313,-10.269],[20.441,-9.167],[20.139,-7.844],[20.436,-6.583],[21.261,-5.629],[22.512,-4.942],[24.086,-4.481],[25.225,-4.184],[25.922,-3.861],[26.271,-3.497],[26.363,-3.066]],"c":true},"ix":2},"nm":"s","mn":"ADBE Vector Shape - Group","hd":false},{"ty":"fl","c":{"a":0,"k":[1,1,1,1],"ix":4},"o":{"a":0,"k":100,"ix":5},"r":1,"nm":"填充 1","mn":"ADBE Vector Graphic - Fill","hd":false},{"ty":"tr","p":{"a":0,"k":[0,0],"ix":2},"a":{"a":0,"k":[0,0],"ix":1},"s":{"a":0,"k":[100,100],"ix":3},"r":{"a":0,"k":0,"ix":6},"o":{"a":0,"k":100,"ix":7},"sk":{"a":0,"k":0,"ix":4},"sa":{"a":0,"k":0,"ix":5},"nm":"变换"}],"nm":"s","np":3,"cix":2,"ix":3,"mn":"ADBE Vector Group","hd":false},{"ty":"gr","it":[{"ind":0,"ty":"sh","ix":1,"ks":{"a":0,"k":{"i":[[0.273,0.174],[0.154,0.294],[0.055,0.39],[0,0.424],[0,0],[-0.055,0.39],[-0.154,0.297],[-0.273,0.178],[-0.431,0],[-0.232,-0.103],[-0.157,-0.174],[-0.086,-0.236],[-0.007,-0.267],[0,0],[0.226,0.537],[0.403,0.376],[0.564,0.202],[0.683,0],[0.639,-0.29],[0.424,-0.506],[0.212,-0.683],[0,-0.786],[0,0],[-0.212,-0.68],[-0.424,-0.502],[-0.643,-0.29],[-0.861,0],[-0.557,0.198],[-0.41,0.359],[-0.239,0.496],[-0.007,0.588],[0,0],[0.092,-0.202],[0.164,-0.144],[0.226,-0.079],[0.273,0]],"o":[[-0.273,-0.174],[-0.154,-0.294],[-0.055,-0.39],[0,0],[0,-0.417],[0.055,-0.39],[0.154,-0.297],[0.273,-0.178],[0.301,0],[0.232,0.103],[0.157,0.174],[0.085,0.236],[0,0],[-0.007,-0.663],[-0.226,-0.537],[-0.403,-0.376],[-0.564,-0.202],[-0.855,0],[-0.639,0.291],[-0.424,0.506],[-0.212,0.684],[0,0],[0,0.786],[0.212,0.68],[0.424,0.502],[0.642,0.29],[0.642,0],[0.557,-0.198],[0.41,-0.359],[0.239,-0.496],[0,0],[-0.007,0.253],[-0.092,0.202],[-0.164,0.144],[-0.226,0.079],[-0.444,0]],"v":[[34.689,-2.446],[34.048,-3.148],[33.735,-4.173],[33.653,-5.394],[33.653,-5.681],[33.735,-6.891],[34.048,-7.921],[34.689,-8.634],[35.745,-8.9],[36.545,-8.747],[37.129,-8.331],[37.493,-7.716],[37.632,-6.962],[40.411,-6.962],[40.062,-8.762],[39.119,-10.131],[37.668,-10.997],[35.796,-11.3],[33.556,-10.864],[31.961,-9.669],[31.008,-7.885],[30.69,-5.681],[30.69,-5.394],[31.008,-3.194],[31.961,-1.42],[33.561,-0.231],[35.817,0.205],[37.616,-0.092],[39.067,-0.928],[40.042,-2.21],[40.411,-3.835],[37.632,-3.835],[37.483,-3.153],[37.099,-2.635],[36.514,-2.302],[35.766,-2.184]],"c":true},"ix":2},"nm":"c","mn":"ADBE Vector Shape - Group","hd":false},{"ty":"fl","c":{"a":0,"k":[1,1,1,1],"ix":4},"o":{"a":0,"k":100,"ix":5},"r":1,"nm":"填充 1","mn":"ADBE Vector Graphic - Fill","hd":false},{"ty":"tr","p":{"a":0,"k":[0,0],"ix":2},"a":{"a":0,"k":[0,0],"ix":1},"s":{"a":0,"k":[100,100],"ix":3},"r":{"a":0,"k":0,"ix":6},"o":{"a":0,"k":100,"ix":7},"sk":{"a":0,"k":0,"ix":4},"sa":{"a":0,"k":0,"ix":5},"nm":"变换"}],"nm":"c","np":3,"cix":2,"ix":4,"mn":"ADBE Vector Group","hd":false},{"ty":"gr","it":[{"ind":0,"ty":"sh","ix":1,"ks":{"a":0,"k":{"i":[[0,0],[-0.232,-0.687],[-0.448,-0.502],[-0.653,-0.284],[-0.841,0],[-0.65,0.284],[-0.448,0.502],[-0.232,0.687],[0,0.814],[0,0],[0.232,0.691],[0.448,0.502],[0.656,0.287],[0.841,0],[0.653,-0.287],[0.444,-0.502],[0.232,-0.69],[0,-0.807]],"o":[[0,0.814],[0.232,0.687],[0.448,0.502],[0.653,0.284],[0.841,0],[0.649,-0.284],[0.448,-0.502],[0.232,-0.687],[0,0],[0,-0.807],[-0.232,-0.69],[-0.448,-0.502],[-0.656,-0.287],[-0.834,0],[-0.653,0.287],[-0.444,0.502],[-0.232,0.691],[0,0]],"v":[[41.641,-5.435],[41.99,-3.184],[43.01,-1.4],[44.661,-0.22],[46.901,0.205],[49.137,-0.22],[50.782,-1.4],[51.803,-3.184],[52.151,-5.435],[52.151,-5.65],[51.803,-7.896],[50.782,-9.685],[49.126,-10.869],[46.881,-11.3],[44.651,-10.869],[43.005,-9.685],[41.99,-7.896],[41.641,-5.65]],"c":true},"ix":2},"nm":"o","mn":"ADBE Vector Shape - Group","hd":false},{"ind":1,"ty":"sh","ix":2,"ks":{"a":0,"k":{"i":[[0,0],[-0.082,0.393],[-0.181,0.297],[-0.291,0.174],[-0.41,0],[-0.294,-0.174],[-0.185,-0.297],[-0.082,-0.393],[0,-0.437],[0,0],[0.082,-0.396],[0.185,-0.29],[0.29,-0.171],[0.41,0],[0.29,0.171],[0.181,0.291],[0.082,0.397],[0,0.451]],"o":[[0,-0.437],[0.082,-0.393],[0.181,-0.297],[0.29,-0.174],[0.417,0],[0.294,0.174],[0.185,0.297],[0.082,0.393],[0,0],[0,0.451],[-0.082,0.397],[-0.185,0.291],[-0.291,0.171],[-0.424,0],[-0.291,-0.171],[-0.181,-0.29],[-0.082,-0.396],[0,0]],"v":[[44.604,-5.65],[44.728,-6.896],[45.122,-7.931],[45.83,-8.639],[46.881,-8.9],[47.947,-8.639],[48.665,-7.931],[49.065,-6.896],[49.188,-5.65],[49.188,-5.435],[49.065,-4.163],[48.665,-3.133],[47.952,-2.44],[46.901,-2.184],[45.83,-2.44],[45.122,-3.133],[44.728,-4.163],[44.604,-5.435]],"c":true},"ix":2},"nm":"o","mn":"ADBE Vector Shape - Group","hd":false},{"ty":"mm","mm":1,"nm":"合并路径 1","mn":"ADBE Vector Filter - Merge","hd":false},{"ty":"fl","c":{"a":0,"k":[1,1,1,1],"ix":4},"o":{"a":0,"k":100,"ix":5},"r":1,"nm":"填充 1","mn":"ADBE Vector Graphic - Fill","hd":false},{"ty":"tr","p":{"a":0,"k":[0,0],"ix":2},"a":{"a":0,"k":[0,0],"ix":1},"s":{"a":0,"k":[100,100],"ix":3},"r":{"a":0,"k":0,"ix":6},"o":{"a":0,"k":100,"ix":7},"sk":{"a":0,"k":0,"ix":4},"sa":{"a":0,"k":0,"ix":5},"nm":"变换"}],"nm":"o","np":5,"cix":2,"ix":5,"mn":"ADBE Vector Group","hd":false},{"ty":"gr","it":[{"ind":0,"ty":"sh","ix":1,"ks":{"a":0,"k":{"i":[[0,0],[0,0],[0,0],[0,0],[0,0],[0,0],[0,0]],"o":[[0,0],[0,0],[0,0],[0,0],[0,0],[0,0],[0,0]],"v":[[55.915,-11.095],[52.818,-11.095],[56.561,0],[59.391,0],[63.133,-11.095],[60.037,-11.095],[57.976,-3.62]],"c":true},"ix":2},"nm":"v","mn":"ADBE Vector Shape - Group","hd":false},{"ty":"fl","c":{"a":0,"k":[1,1,1,1],"ix":4},"o":{"a":0,"k":100,"ix":5},"r":1,"nm":"填充 1","mn":"ADBE Vector Graphic - Fill","hd":false},{"ty":"tr","p":{"a":0,"k":[0,0],"ix":2},"a":{"a":0,"k":[0,0],"ix":1},"s":{"a":0,"k":[100,100],"ix":3},"r":{"a":0,"k":0,"ix":6},"o":{"a":0,"k":100,"ix":7},"sk":{"a":0,"k":0,"ix":4},"sa":{"a":0,"k":0,"ix":5},"nm":"变换"}],"nm":"v","np":3,"cix":2,"ix":6,"mn":"ADBE Vector Group","hd":false},{"ty":"gr","it":[{"ind":0,"ty":"sh","ix":1,"ks":{"a":0,"k":{"i":[[-0.455,0.113],[-0.362,0.188],[-0.267,0.239],[-0.178,0.253],[0,0],[0.458,-0.202],[0.54,0],[0.308,0.116],[0.229,0.209],[0.147,0.294],[0.048,0.362],[0,0],[0,0],[0.208,0.67],[0.414,0.475],[0.608,0.263],[0.8,0],[0.639,-0.284],[0.448,-0.506],[0.243,-0.701],[0,-0.841],[0,0],[-0.25,-0.653],[-0.475,-0.485],[-0.68,-0.28],[-0.861,0]],"o":[[0.455,-0.113],[0.362,-0.188],[0.267,-0.239],[0,0],[-0.328,0.424],[-0.458,0.202],[-0.383,0],[-0.308,-0.116],[-0.229,-0.208],[-0.147,-0.294],[0,0],[0,0],[0,-0.82],[-0.209,-0.67],[-0.414,-0.475],[-0.609,-0.263],[-0.793,0],[-0.639,0.284],[-0.448,0.506],[-0.243,0.701],[0,0],[0,0.745],[0.249,0.653],[0.475,0.485],[0.68,0.28],[0.54,0]],"v":[[70.901,0.036],[72.126,-0.415],[73.069,-1.056],[73.736,-1.794],[72.28,-3.425],[71.101,-2.487],[69.604,-2.184],[68.568,-2.358],[67.763,-2.845],[67.199,-3.599],[66.907,-4.583],[73.972,-4.583],[73.972,-5.845],[73.659,-8.08],[72.726,-9.798],[71.193,-10.905],[69.081,-11.3],[66.932,-10.874],[65.302,-9.69],[64.266,-7.88],[63.902,-5.568],[63.902,-5.168],[64.277,-3.071],[65.364,-1.364],[67.096,-0.215],[69.409,0.205]],"c":true},"ix":2},"nm":"e","mn":"ADBE Vector Shape - Group","hd":false},{"ind":1,"ty":"sh","ix":2,"ks":{"a":0,"k":{"i":[[-0.25,-0.103],[-0.161,-0.185],[-0.079,-0.253],[-0.007,-0.294],[0,0],[0,0],[-0.109,0.28],[-0.174,0.202],[-0.243,0.113],[-0.321,0]],"o":[[0.249,0.103],[0.161,0.185],[0.079,0.253],[0,0],[0,0],[0.048,-0.342],[0.109,-0.28],[0.174,-0.202],[0.243,-0.113],[0.342,0]],"v":[[69.957,-8.747],[70.573,-8.316],[70.931,-7.66],[71.06,-6.839],[71.06,-6.604],[66.938,-6.604],[67.173,-7.537],[67.599,-8.26],[68.224,-8.731],[69.07,-8.9]],"c":true},"ix":2},"nm":"e","mn":"ADBE Vector Shape - Group","hd":false},{"ty":"mm","mm":1,"nm":"合并路径 1","mn":"ADBE Vector Filter - Merge","hd":false},{"ty":"fl","c":{"a":0,"k":[1,1,1,1],"ix":4},"o":{"a":0,"k":100,"ix":5},"r":1,"nm":"填充 1","mn":"ADBE Vector Graphic - Fill","hd":false},{"ty":"tr","p":{"a":0,"k":[0,0],"ix":2},"a":{"a":0,"k":[0,0],"ix":1},"s":{"a":0,"k":[100,100],"ix":3},"r":{"a":0,"k":0,"ix":6},"o":{"a":0,"k":100,"ix":7},"sk":{"a":0,"k":0,"ix":4},"sa":{"a":0,"k":0,"ix":5},"nm":"变换"}],"nm":"e","np":5,"cix":2,"ix":7,"mn":"ADBE Vector Group","hd":false},{"ty":"gr","it":[{"ind":0,"ty":"sh","ix":1,"ks":{"a":0,"k":{"i":[[0,0],[0.174,0.027],[0.157,0],[0.41,-0.27],[0.28,-0.478],[0,0],[0,0],[0,0],[0,0],[0,0],[-0.359,0.195],[-0.581,0],[-0.202,-0.017],[-0.15,-0.021]],"o":[[-0.109,-0.034],[-0.174,-0.027],[-0.547,0],[-0.41,0.27],[0,0],[0,0],[0,0],[0,0],[0,0],[0.171,-0.369],[0.359,-0.195],[0.157,0],[0.202,0.017],[0,0]],"v":[[81.929,-11.167],[81.503,-11.259],[81.006,-11.3],[79.57,-10.895],[78.535,-9.772],[78.453,-11.095],[75.653,-11.095],[75.653,0],[78.617,0],[78.617,-7.26],[79.411,-8.106],[80.821,-8.398],[81.36,-8.372],[81.888,-8.316]],"c":true},"ix":2},"nm":"r","mn":"ADBE Vector Shape - Group","hd":false},{"ty":"fl","c":{"a":0,"k":[1,1,1,1],"ix":4},"o":{"a":0,"k":100,"ix":5},"r":1,"nm":"填充 1","mn":"ADBE Vector Graphic - Fill","hd":false},{"ty":"tr","p":{"a":0,"k":[0,0],"ix":2},"a":{"a":0,"k":[0,0],"ix":1},"s":{"a":0,"k":[100,100],"ix":3},"r":{"a":0,"k":0,"ix":6},"o":{"a":0,"k":100,"ix":7},"sk":{"a":0,"k":0,"ix":4},"sa":{"a":0,"k":0,"ix":5},"nm":"变换"}],"nm":"r","np":3,"cix":2,"ix":8,"mn":"ADBE Vector Group","hd":false}],"ip":0,"op":1001,"st":0,"bm":0},{"ddd":0,"ind":5,"ty":4,"nm":"“Share”轮廓","sr":1,"ks":{"o":{"a":1,"k":[{"i":{"x":[0.25],"y":[1]},"o":{"x":[0.167],"y":[0.167]},"n":["0p25_1_0p167_0p167"],"t":65,"s":[0],"e":[100]},{"t":76}],"ix":11},"r":{"a":0,"k":0,"ix":10},"p":{"a":1,"k":[{"i":{"x":0.25,"y":1},"o":{"x":0.167,"y":0.167},"n":"0p25_1_0p167_0p167","t":65,"s":[211.911,725.301,0],"e":[211.911,677.301,0],"to":[0,-8,0],"ti":[0,8,0]},{"i":{"x":0.25,"y":0.25},"o":{"x":0.167,"y":0.167},"n":"0p25_0p25_0p167_0p167","t":76,"s":[211.911,677.301,0],"e":[211.911,677.301,0],"to":[0,0,0],"ti":[0,0,0]},{"i":{"x":0.25,"y":1},"o":{"x":0.167,"y":0.167},"n":"0p25_1_0p167_0p167","t":91,"s":[211.911,677.301,0],"e":[144.911,677.301,0],"to":[-11.1666679382324,0,0],"ti":[11.1666679382324,0,0]},{"t":100}],"ix":2},"a":{"a":0,"k":[0,0,0],"ix":1},"s":{"a":0,"k":[293.183,293.183,100],"ix":6}},"ao":0,"shapes":[{"ty":"gr","it":[{"ind":0,"ty":"sh","ix":1,"ks":{"a":0,"k":{"i":[[0.092,-0.208],[0.191,-0.15],[0.294,-0.085],[0.396,0],[0.362,0.089],[0.256,0.195],[0.144,0.314],[0,0.451],[0,0],[-0.161,-0.461],[-0.284,-0.362],[-0.383,-0.267],[-0.448,-0.178],[-0.492,-0.085],[-0.492,0],[-0.667,0.188],[-0.472,0.352],[-0.256,0.513],[0,0.656],[0.212,0.485],[0.414,0.39],[0.619,0.308],[0.813,0.253],[0.502,0.332],[0,0.492],[-0.099,0.212],[-0.195,0.157],[-0.297,0.089],[-0.403,0],[-0.308,-0.106],[-0.205,-0.191],[-0.099,-0.267],[0,-0.314],[0,0],[0.26,0.564],[0.478,0.41],[0.677,0.229],[0.827,0],[0.673,-0.202],[0.489,-0.362],[0.27,-0.516],[0,-0.622],[-0.263,-0.485],[-0.455,-0.373],[-0.605,-0.273],[-0.684,-0.219],[-0.379,-0.171],[-0.215,-0.178],[-0.075,-0.208],[0,-0.26]],"o":[[-0.092,0.209],[-0.191,0.15],[-0.294,0.086],[-0.444,0],[-0.362,-0.089],[-0.256,-0.195],[-0.144,-0.314],[0,0],[0,0.561],[0.161,0.461],[0.284,0.362],[0.383,0.267],[0.448,0.178],[0.492,0.085],[0.82,0],[0.667,-0.188],[0.472,-0.352],[0.256,-0.513],[0,-0.615],[-0.212,-0.485],[-0.414,-0.39],[-0.619,-0.308],[-0.971,-0.287],[-0.502,-0.331],[0,-0.239],[0.099,-0.212],[0.195,-0.157],[0.297,-0.089],[0.417,0],[0.308,0.106],[0.205,0.191],[0.099,0.267],[0,0],[0,-0.67],[-0.26,-0.564],[-0.479,-0.41],[-0.677,-0.229],[-0.807,0],[-0.673,0.202],[-0.489,0.362],[-0.27,0.516],[0,0.65],[0.263,0.485],[0.455,0.373],[0.605,0.273],[0.601,0.191],[0.379,0.171],[0.215,0.178],[0.075,0.209],[0,0.239]],"v":[[8.936,-3.245],[8.511,-2.707],[7.783,-2.353],[6.747,-2.225],[5.537,-2.358],[4.609,-2.784],[4.009,-3.548],[3.794,-4.696],[0.708,-4.696],[0.948,-3.163],[1.615,-1.928],[2.615,-0.984],[3.861,-0.318],[5.271,0.077],[6.747,0.205],[8.977,-0.077],[10.685,-0.887],[11.777,-2.184],[12.161,-3.938],[11.843,-5.588],[10.905,-6.901],[9.357,-7.947],[7.208,-8.788],[4.999,-9.716],[4.245,-10.951],[4.394,-11.628],[4.835,-12.182],[5.573,-12.551],[6.624,-12.684],[7.711,-12.525],[8.48,-12.079],[8.936,-11.392],[9.085,-10.521],[12.161,-10.521],[11.771,-12.371],[10.664,-13.833],[8.931,-14.791],[6.675,-15.135],[4.455,-14.832],[2.712,-13.986],[1.574,-12.669],[1.169,-10.961],[1.564,-9.259],[2.64,-7.972],[4.23,-7.003],[6.163,-6.265],[7.634,-5.722],[8.526,-5.199],[8.962,-4.619],[9.075,-3.917]],"c":true},"ix":2},"nm":"S","mn":"ADBE Vector Shape - Group","hd":false},{"ty":"fl","c":{"a":0,"k":[1,1,1,1],"ix":4},"o":{"a":0,"k":100,"ix":5},"r":1,"nm":"填充 1","mn":"ADBE Vector Graphic - Fill","hd":false},{"ty":"tr","p":{"a":0,"k":[0,0],"ix":2},"a":{"a":0,"k":[0,0],"ix":1},"s":{"a":0,"k":[100,100],"ix":3},"r":{"a":0,"k":0,"ix":6},"o":{"a":0,"k":100,"ix":7},"sk":{"a":0,"k":0,"ix":4},"sa":{"a":0,"k":0,"ix":5},"nm":"变换"}],"nm":"S","np":3,"cix":2,"ix":1,"mn":"ADBE Vector Group","hd":false},{"ty":"gr","it":[{"ind":0,"ty":"sh","ix":1,"ks":{"a":0,"k":{"i":[[0,0],[0,0],[0,0],[0,0],[0,0],[-0.308,0.181],[-0.465,0],[-0.222,-0.062],[-0.15,-0.147],[-0.079,-0.239],[0,-0.355],[0,0],[0,0],[0,0],[0.174,0.547],[0.321,0.345],[0.451,0.154],[0.547,0],[0.496,-0.249],[0.369,-0.444]],"o":[[0,0],[0,0],[0,0],[0,0],[0.178,-0.308],[0.308,-0.181],[0.28,0],[0.222,0.062],[0.15,0.147],[0.079,0.239],[0,0],[0,0],[0,0],[0,-0.779],[-0.174,-0.547],[-0.321,-0.345],[-0.451,-0.154],[-0.615,0],[-0.496,0.25],[0,0]],"v":[[16.939,-15.75],[13.976,-15.75],[13.976,0],[16.939,0],[16.939,-7.885],[17.667,-8.618],[18.826,-8.89],[19.58,-8.798],[20.139,-8.485],[20.482,-7.906],[20.6,-7.014],[20.6,0],[23.563,0],[23.563,-6.993],[23.302,-8.982],[22.559,-10.321],[21.4,-11.069],[19.903,-11.3],[18.237,-10.926],[16.939,-9.885]],"c":true},"ix":2},"nm":"h","mn":"ADBE Vector Shape - Group","hd":false},{"ty":"fl","c":{"a":0,"k":[1,1,1,1],"ix":4},"o":{"a":0,"k":100,"ix":5},"r":1,"nm":"填充 1","mn":"ADBE Vector Graphic - Fill","hd":false},{"ty":"tr","p":{"a":0,"k":[0,0],"ix":2},"a":{"a":0,"k":[0,0],"ix":1},"s":{"a":0,"k":[100,100],"ix":3},"r":{"a":0,"k":0,"ix":6},"o":{"a":0,"k":100,"ix":7},"sk":{"a":0,"k":0,"ix":4},"sa":{"a":0,"k":0,"ix":5},"nm":"变换"}],"nm":"h","np":3,"cix":2,"ix":2,"mn":"ADBE Vector Group","hd":false},{"ty":"gr","it":[{"ind":0,"ty":"sh","ix":1,"ks":{"a":0,"k":{"i":[[0,0],[0,0],[0.055,0.161],[0.034,0.202],[0.021,0.25],[0,0.314],[0,0],[0.222,0.489],[0.396,0.325],[0.547,0.164],[0.642,0],[0.581,-0.188],[0.41,-0.321],[0.222,-0.431],[0,-0.478],[0,0],[-0.284,0.239],[-0.499,0],[-0.263,-0.308],[0,-0.513],[0,0],[0,0],[0.639,-0.164],[0.431,-0.314],[0.215,-0.451],[0,-0.581],[-0.191,-0.407],[-0.338,-0.294],[-0.461,-0.164],[-0.533,0],[-0.455,0.232],[-0.301,0.335],[-0.137,-0.267]],"o":[[0,0],[-0.075,-0.144],[-0.055,-0.161],[-0.034,-0.202],[-0.021,-0.249],[0,0],[0,-0.649],[-0.222,-0.489],[-0.397,-0.325],[-0.547,-0.164],[-0.718,0],[-0.581,0.188],[-0.41,0.321],[-0.222,0.431],[0,0],[0,-0.417],[0.284,-0.239],[0.567,0],[0.263,0.308],[0,0],[0,0],[-0.848,0],[-0.639,0.164],[-0.431,0.314],[-0.215,0.451],[0,0.485],[0.191,0.407],[0.338,0.294],[0.461,0.164],[0.656,0],[0.455,-0.232],[0.062,0.397],[0,0]],"v":[[35.222,0],[35.222,-0.174],[35.027,-0.631],[34.894,-1.174],[34.812,-1.851],[34.781,-2.697],[34.781,-7.393],[34.448,-9.1],[33.52,-10.321],[32.105,-11.054],[30.321,-11.3],[28.373,-11.018],[26.886,-10.254],[25.937,-9.126],[25.604,-7.762],[28.567,-7.762],[28.993,-8.747],[30.167,-9.105],[31.413,-8.644],[31.808,-7.414],[31.808,-6.778],[30.485,-6.778],[28.255,-6.532],[26.65,-5.814],[25.681,-4.666],[25.358,-3.117],[25.645,-1.779],[26.44,-0.728],[27.639,-0.041],[29.131,0.205],[30.798,-0.144],[31.931,-0.995],[32.228,0]],"c":true},"ix":2},"nm":"a","mn":"ADBE Vector Shape - Group","hd":false},{"ind":1,"ty":"sh","ix":2,"ks":{"a":0,"k":{"i":[[0.26,0.239],[0,0.369],[-0.089,0.209],[-0.185,0.154],[-0.287,0.086],[-0.39,0],[0,0],[0,0],[0.126,-0.13],[0.171,-0.099],[0.215,-0.062],[0.253,0]],"o":[[-0.26,-0.239],[0,-0.246],[0.089,-0.208],[0.185,-0.154],[0.287,-0.085],[0,0],[0,0],[-0.075,0.137],[-0.127,0.13],[-0.171,0.099],[-0.215,0.062],[-0.451,0]],"v":[[28.711,-2.42],[28.321,-3.333],[28.455,-4.014],[28.865,-4.558],[29.572,-4.917],[30.587,-5.045],[31.808,-5.045],[31.808,-3.138],[31.505,-2.738],[31.059,-2.394],[30.48,-2.153],[29.777,-2.061]],"c":true},"ix":2},"nm":"a","mn":"ADBE Vector Shape - Group","hd":false},{"ty":"mm","mm":1,"nm":"合并路径 1","mn":"ADBE Vector Filter - Merge","hd":false},{"ty":"fl","c":{"a":0,"k":[1,1,1,1],"ix":4},"o":{"a":0,"k":100,"ix":5},"r":1,"nm":"填充 1","mn":"ADBE Vector Graphic - Fill","hd":false},{"ty":"tr","p":{"a":0,"k":[0,0],"ix":2},"a":{"a":0,"k":[0,0],"ix":1},"s":{"a":0,"k":[100,100],"ix":3},"r":{"a":0,"k":0,"ix":6},"o":{"a":0,"k":100,"ix":7},"sk":{"a":0,"k":0,"ix":4},"sa":{"a":0,"k":0,"ix":5},"nm":"变换"}],"nm":"a","np":5,"cix":2,"ix":3,"mn":"ADBE Vector Group","hd":false},{"ty":"gr","it":[{"ind":0,"ty":"sh","ix":1,"ks":{"a":0,"k":{"i":[[0,0],[0.174,0.027],[0.157,0],[0.41,-0.27],[0.28,-0.478],[0,0],[0,0],[0,0],[0,0],[0,0],[-0.359,0.195],[-0.581,0],[-0.202,-0.017],[-0.15,-0.021]],"o":[[-0.109,-0.034],[-0.174,-0.027],[-0.547,0],[-0.41,0.27],[0,0],[0,0],[0,0],[0,0],[0,0],[0.171,-0.369],[0.359,-0.195],[0.157,0],[0.202,0.017],[0,0]],"v":[[43.333,-11.167],[42.907,-11.259],[42.41,-11.3],[40.975,-10.895],[39.939,-9.772],[39.857,-11.095],[37.058,-11.095],[37.058,0],[40.021,0],[40.021,-7.26],[40.816,-8.106],[42.226,-8.398],[42.764,-8.372],[43.292,-8.316]],"c":true},"ix":2},"nm":"r","mn":"ADBE Vector Shape - Group","hd":false},{"ty":"fl","c":{"a":0,"k":[1,1,1,1],"ix":4},"o":{"a":0,"k":100,"ix":5},"r":1,"nm":"填充 1","mn":"ADBE Vector Graphic - Fill","hd":false},{"ty":"tr","p":{"a":0,"k":[0,0],"ix":2},"a":{"a":0,"k":[0,0],"ix":1},"s":{"a":0,"k":[100,100],"ix":3},"r":{"a":0,"k":0,"ix":6},"o":{"a":0,"k":100,"ix":7},"sk":{"a":0,"k":0,"ix":4},"sa":{"a":0,"k":0,"ix":5},"nm":"变换"}],"nm":"r","np":3,"cix":2,"ix":4,"mn":"ADBE Vector Group","hd":false},{"ty":"gr","it":[{"ind":0,"ty":"sh","ix":1,"ks":{"a":0,"k":{"i":[[-0.455,0.113],[-0.362,0.188],[-0.267,0.239],[-0.178,0.253],[0,0],[0.458,-0.202],[0.54,0],[0.308,0.116],[0.229,0.209],[0.147,0.294],[0.048,0.362],[0,0],[0,0],[0.208,0.67],[0.414,0.475],[0.608,0.263],[0.8,0],[0.639,-0.284],[0.448,-0.506],[0.243,-0.701],[0,-0.841],[0,0],[-0.25,-0.653],[-0.475,-0.485],[-0.68,-0.28],[-0.861,0]],"o":[[0.455,-0.113],[0.362,-0.188],[0.267,-0.239],[0,0],[-0.328,0.424],[-0.458,0.202],[-0.383,0],[-0.308,-0.116],[-0.229,-0.208],[-0.147,-0.294],[0,0],[0,0],[0,-0.82],[-0.209,-0.67],[-0.414,-0.475],[-0.609,-0.263],[-0.793,0],[-0.639,0.284],[-0.448,0.506],[-0.243,0.701],[0,0],[0,0.745],[0.249,0.653],[0.475,0.485],[0.68,0.28],[0.54,0]],"v":[[51.121,0.036],[52.346,-0.415],[53.29,-1.056],[53.956,-1.794],[52.5,-3.425],[51.321,-2.487],[49.824,-2.184],[48.788,-2.358],[47.983,-2.845],[47.419,-3.599],[47.127,-4.583],[54.192,-4.583],[54.192,-5.845],[53.879,-8.08],[52.946,-9.798],[51.413,-10.905],[49.301,-11.3],[47.153,-10.874],[45.522,-9.69],[44.487,-7.88],[44.123,-5.568],[44.123,-5.168],[44.497,-3.071],[45.584,-1.364],[47.317,-0.215],[49.629,0.205]],"c":true},"ix":2},"nm":"e","mn":"ADBE Vector Shape - Group","hd":false},{"ind":1,"ty":"sh","ix":2,"ks":{"a":0,"k":{"i":[[-0.25,-0.103],[-0.161,-0.185],[-0.079,-0.253],[-0.007,-0.294],[0,0],[0,0],[-0.109,0.28],[-0.174,0.202],[-0.243,0.113],[-0.321,0]],"o":[[0.249,0.103],[0.161,0.185],[0.079,0.253],[0,0],[0,0],[0.048,-0.342],[0.109,-0.28],[0.174,-0.202],[0.243,-0.113],[0.342,0]],"v":[[50.177,-8.747],[50.793,-8.316],[51.152,-7.66],[51.28,-6.839],[51.28,-6.604],[47.158,-6.604],[47.394,-7.537],[47.819,-8.26],[48.445,-8.731],[49.291,-8.9]],"c":true},"ix":2},"nm":"e","mn":"ADBE Vector Shape - Group","hd":false},{"ty":"mm","mm":1,"nm":"合并路径 1","mn":"ADBE Vector Filter - Merge","hd":false},{"ty":"fl","c":{"a":0,"k":[1,1,1,1],"ix":4},"o":{"a":0,"k":100,"ix":5},"r":1,"nm":"填充 1","mn":"ADBE Vector Graphic - Fill","hd":false},{"ty":"tr","p":{"a":0,"k":[0,0],"ix":2},"a":{"a":0,"k":[0,0],"ix":1},"s":{"a":0,"k":[100,100],"ix":3},"r":{"a":0,"k":0,"ix":6},"o":{"a":0,"k":100,"ix":7},"sk":{"a":0,"k":0,"ix":4},"sa":{"a":0,"k":0,"ix":5},"nm":"变换"}],"nm":"e","np":5,"cix":2,"ix":5,"mn":"ADBE Vector Group","hd":false}],"ip":0,"op":1001,"st":0,"bm":0},{"ddd":0,"ind":6,"ty":4,"nm":"“interests”轮廓","sr":1,"ks":{"o":{"a":1,"k":[{"i":{"x":[0.25],"y":[1]},"o":{"x":[0.167],"y":[0.167]},"n":["0p25_1_0p167_0p167"],"t":91,"s":[0],"e":[100]},{"t":100}],"ix":11},"r":{"a":0,"k":0,"ix":10},"p":{"a":1,"k":[{"i":{"x":0.25,"y":1},"o":{"x":0.167,"y":0.167},"n":"0p25_1_0p167_0p167","t":91,"s":[388.599,676.023,0],"e":[321.599,676.023,0],"to":[-11.1666603088379,0,0],"ti":[11.1666603088379,0,0]},{"t":100}],"ix":2},"a":{"a":0,"k":[0,0,0],"ix":1},"s":{"a":0,"k":[293.183,293.183,100],"ix":6}},"ao":0,"shapes":[{"ty":"gr","it":[{"ind":0,"ty":"sh","ix":1,"ks":{"a":0,"k":{"i":[[0,0],[0,0],[0,0],[0,0]],"o":[[0,0],[0,0],[0,0],[0,0]],"v":[[4.266,-11.095],[1.292,-11.095],[1.292,0],[4.266,0]],"c":true},"ix":2},"nm":"i","mn":"ADBE Vector Shape - Group","hd":false},{"ind":1,"ty":"sh","ix":2,"ks":{"a":0,"k":{"i":[[-0.079,-0.188],[-0.144,-0.137],[-0.205,-0.075],[-0.253,0],[-0.205,0.075],[-0.144,0.137],[-0.079,0.188],[0,0.226],[0.079,0.188],[0.144,0.137],[0.205,0.075],[0.253,0],[0.297,-0.287],[0,-0.444]],"o":[[0.079,0.188],[0.144,0.137],[0.205,0.075],[0.253,0],[0.205,-0.075],[0.144,-0.137],[0.079,-0.188],[0,-0.219],[-0.079,-0.188],[-0.144,-0.137],[-0.205,-0.075],[-0.513,0],[-0.297,0.287],[0,0.226]],"v":[[1.236,-13.345],[1.569,-12.858],[2.092,-12.541],[2.779,-12.428],[3.466,-12.541],[3.989,-12.858],[4.322,-13.345],[4.44,-13.966],[4.322,-14.576],[3.989,-15.063],[3.466,-15.381],[2.779,-15.494],[1.564,-15.063],[1.118,-13.966]],"c":true},"ix":2},"nm":"i","mn":"ADBE Vector Shape - Group","hd":false},{"ty":"mm","mm":1,"nm":"合并路径 1","mn":"ADBE Vector Filter - Merge","hd":false},{"ty":"fl","c":{"a":0,"k":[1,1,1,1],"ix":4},"o":{"a":0,"k":100,"ix":5},"r":1,"nm":"填充 1","mn":"ADBE Vector Graphic - Fill","hd":false},{"ty":"tr","p":{"a":0,"k":[0,0],"ix":2},"a":{"a":0,"k":[0,0],"ix":1},"s":{"a":0,"k":[100,100],"ix":3},"r":{"a":0,"k":0,"ix":6},"o":{"a":0,"k":100,"ix":7},"sk":{"a":0,"k":0,"ix":4},"sa":{"a":0,"k":0,"ix":5},"nm":"变换"}],"nm":"i","np":5,"cix":2,"ix":1,"mn":"ADBE Vector Group","hd":false},{"ty":"gr","it":[{"ind":0,"ty":"sh","ix":1,"ks":{"a":0,"k":{"i":[[0,0],[0,0],[0,0],[0,0],[-0.311,0.191],[-0.438,0],[-0.219,-0.058],[-0.15,-0.137],[-0.079,-0.232],[0,-0.355],[0,0],[0,0],[0,0],[0.167,0.54],[0.308,0.335],[0.431,0.147],[0.526,0],[0.54,-0.256],[0.383,-0.478],[0,0]],"o":[[0,0],[0,0],[0,0],[0.191,-0.328],[0.311,-0.191],[0.287,0],[0.219,0.058],[0.15,0.137],[0.079,0.232],[0,0],[0,0],[0,0],[0,-0.786],[-0.168,-0.54],[-0.308,-0.335],[-0.431,-0.147],[-0.663,0],[-0.54,0.256],[0,0],[0,0]],"v":[[6.645,-11.095],[6.645,0],[9.608,0],[9.608,-7.824],[10.362,-8.603],[11.484,-8.89],[12.243,-8.803],[12.797,-8.511],[13.14,-7.957],[13.258,-7.075],[13.258,0],[16.222,0],[16.222,-7.055],[15.97,-9.044],[15.258,-10.356],[14.15,-11.079],[12.715,-11.3],[10.91,-10.915],[9.526,-9.813],[9.434,-11.095]],"c":true},"ix":2},"nm":"n","mn":"ADBE Vector Shape - Group","hd":false},{"ty":"fl","c":{"a":0,"k":[1,1,1,1],"ix":4},"o":{"a":0,"k":100,"ix":5},"r":1,"nm":"填充 1","mn":"ADBE Vector Graphic - Fill","hd":false},{"ty":"tr","p":{"a":0,"k":[0,0],"ix":2},"a":{"a":0,"k":[0,0],"ix":1},"s":{"a":0,"k":[100,100],"ix":3},"r":{"a":0,"k":0,"ix":6},"o":{"a":0,"k":100,"ix":7},"sk":{"a":0,"k":0,"ix":4},"sa":{"a":0,"k":0,"ix":5},"nm":"变换"}],"nm":"n","np":3,"cix":2,"ix":2,"mn":"ADBE Vector Group","hd":false},{"ty":"gr","it":[{"ind":0,"ty":"sh","ix":1,"ks":{"a":0,"k":{"i":[[0,0],[0,0],[0,0],[0,0],[0,0],[0,0],[-0.15,-0.417],[-0.277,-0.26],[-0.39,-0.12],[-0.485,0],[-0.291,0.051],[-0.246,0.075],[0,0],[0.147,-0.014],[0.178,0],[0.14,0.031],[0.096,0.086],[0.048,0.15],[0,0.232],[0,0],[0,0],[0,0],[0,0],[0,0]],"o":[[0,0],[0,0],[0,0],[0,0],[0,0],[0,0.588],[0.15,0.417],[0.277,0.26],[0.39,0.12],[0.369,0],[0.29,-0.051],[0,0],[-0.109,0.021],[-0.147,0.014],[-0.191,0],[-0.14,-0.031],[-0.096,-0.085],[-0.048,-0.15],[0,0],[0,0],[0,0],[0,0],[0,0],[0,0]],"v":[[19.052,-13.822],[19.052,-11.095],[17.432,-11.095],[17.432,-8.921],[19.052,-8.921],[19.052,-3.066],[19.277,-1.559],[19.918,-0.543],[20.918,0.026],[22.23,0.205],[23.22,0.128],[24.025,-0.062],[24.025,-2.307],[23.64,-2.256],[23.153,-2.235],[22.656,-2.281],[22.302,-2.456],[22.087,-2.81],[22.015,-3.384],[22.015,-8.921],[23.912,-8.921],[23.912,-11.095],[22.015,-11.095],[22.015,-13.822]],"c":true},"ix":2},"nm":"t","mn":"ADBE Vector Shape - Group","hd":false},{"ty":"fl","c":{"a":0,"k":[1,1,1,1],"ix":4},"o":{"a":0,"k":100,"ix":5},"r":1,"nm":"填充 1","mn":"ADBE Vector Graphic - Fill","hd":false},{"ty":"tr","p":{"a":0,"k":[0,0],"ix":2},"a":{"a":0,"k":[0,0],"ix":1},"s":{"a":0,"k":[100,100],"ix":3},"r":{"a":0,"k":0,"ix":6},"o":{"a":0,"k":100,"ix":7},"sk":{"a":0,"k":0,"ix":4},"sa":{"a":0,"k":0,"ix":5},"nm":"变换"}],"nm":"t","np":3,"cix":2,"ix":3,"mn":"ADBE Vector Group","hd":false},{"ty":"gr","it":[{"ind":0,"ty":"sh","ix":1,"ks":{"a":0,"k":{"i":[[-0.455,0.113],[-0.362,0.188],[-0.267,0.239],[-0.178,0.253],[0,0],[0.458,-0.202],[0.54,0],[0.308,0.116],[0.229,0.209],[0.147,0.294],[0.048,0.362],[0,0],[0,0],[0.208,0.67],[0.414,0.475],[0.608,0.263],[0.8,0],[0.639,-0.284],[0.448,-0.506],[0.243,-0.701],[0,-0.841],[0,0],[-0.25,-0.653],[-0.475,-0.485],[-0.68,-0.28],[-0.861,0]],"o":[[0.455,-0.113],[0.362,-0.188],[0.267,-0.239],[0,0],[-0.328,0.424],[-0.458,0.202],[-0.383,0],[-0.308,-0.116],[-0.229,-0.208],[-0.147,-0.294],[0,0],[0,0],[0,-0.82],[-0.209,-0.67],[-0.414,-0.475],[-0.609,-0.263],[-0.793,0],[-0.639,0.284],[-0.448,0.506],[-0.243,0.701],[0,0],[0,0.745],[0.249,0.653],[0.475,0.485],[0.68,0.28],[0.54,0]],"v":[[32.161,0.036],[33.387,-0.415],[34.33,-1.056],[34.997,-1.794],[33.541,-3.425],[32.361,-2.487],[30.864,-2.184],[29.829,-2.358],[29.024,-2.845],[28.46,-3.599],[28.167,-4.583],[35.232,-4.583],[35.232,-5.845],[34.92,-8.08],[33.987,-9.798],[32.454,-10.905],[30.341,-11.3],[28.193,-10.874],[26.563,-9.69],[25.527,-7.88],[25.163,-5.568],[25.163,-5.168],[25.537,-3.071],[26.624,-1.364],[28.357,-0.215],[30.669,0.205]],"c":true},"ix":2},"nm":"e","mn":"ADBE Vector Shape - Group","hd":false},{"ind":1,"ty":"sh","ix":2,"ks":{"a":0,"k":{"i":[[-0.25,-0.103],[-0.161,-0.185],[-0.079,-0.253],[-0.007,-0.294],[0,0],[0,0],[-0.109,0.28],[-0.174,0.202],[-0.243,0.113],[-0.321,0]],"o":[[0.249,0.103],[0.161,0.185],[0.079,0.253],[0,0],[0,0],[0.048,-0.342],[0.109,-0.28],[0.174,-0.202],[0.243,-0.113],[0.342,0]],"v":[[31.218,-8.747],[31.833,-8.316],[32.192,-7.66],[32.32,-6.839],[32.32,-6.604],[28.198,-6.604],[28.434,-7.537],[28.86,-8.26],[29.485,-8.731],[30.331,-8.9]],"c":true},"ix":2},"nm":"e","mn":"ADBE Vector Shape - Group","hd":false},{"ty":"mm","mm":1,"nm":"合并路径 1","mn":"ADBE Vector Filter - Merge","hd":false},{"ty":"fl","c":{"a":0,"k":[1,1,1,1],"ix":4},"o":{"a":0,"k":100,"ix":5},"r":1,"nm":"填充 1","mn":"ADBE Vector Graphic - Fill","hd":false},{"ty":"tr","p":{"a":0,"k":[0,0],"ix":2},"a":{"a":0,"k":[0,0],"ix":1},"s":{"a":0,"k":[100,100],"ix":3},"r":{"a":0,"k":0,"ix":6},"o":{"a":0,"k":100,"ix":7},"sk":{"a":0,"k":0,"ix":4},"sa":{"a":0,"k":0,"ix":5},"nm":"变换"}],"nm":"e","np":5,"cix":2,"ix":4,"mn":"ADBE Vector Group","hd":false},{"ty":"gr","it":[{"ind":0,"ty":"sh","ix":1,"ks":{"a":0,"k":{"i":[[0,0],[0.174,0.027],[0.157,0],[0.41,-0.27],[0.28,-0.478],[0,0],[0,0],[0,0],[0,0],[0,0],[-0.359,0.195],[-0.581,0],[-0.202,-0.017],[-0.15,-0.021]],"o":[[-0.109,-0.034],[-0.174,-0.027],[-0.547,0],[-0.41,0.27],[0,0],[0,0],[0,0],[0,0],[0,0],[0.171,-0.369],[0.359,-0.195],[0.157,0],[0.202,0.017],[0,0]],"v":[[43.189,-11.167],[42.764,-11.259],[42.267,-11.3],[40.831,-10.895],[39.795,-9.772],[39.713,-11.095],[36.914,-11.095],[36.914,0],[39.877,0],[39.877,-7.26],[40.672,-8.106],[42.082,-8.398],[42.62,-8.372],[43.148,-8.316]],"c":true},"ix":2},"nm":"r","mn":"ADBE Vector Shape - Group","hd":false},{"ty":"fl","c":{"a":0,"k":[1,1,1,1],"ix":4},"o":{"a":0,"k":100,"ix":5},"r":1,"nm":"填充 1","mn":"ADBE Vector Graphic - Fill","hd":false},{"ty":"tr","p":{"a":0,"k":[0,0],"ix":2},"a":{"a":0,"k":[0,0],"ix":1},"s":{"a":0,"k":[100,100],"ix":3},"r":{"a":0,"k":0,"ix":6},"o":{"a":0,"k":100,"ix":7},"sk":{"a":0,"k":0,"ix":4},"sa":{"a":0,"k":0,"ix":5},"nm":"变换"}],"nm":"r","np":3,"cix":2,"ix":5,"mn":"ADBE Vector Group","hd":false},{"ty":"gr","it":[{"ind":0,"ty":"sh","ix":1,"ks":{"a":0,"k":{"i":[[-0.455,0.113],[-0.362,0.188],[-0.267,0.239],[-0.178,0.253],[0,0],[0.458,-0.202],[0.54,0],[0.308,0.116],[0.229,0.209],[0.147,0.294],[0.048,0.362],[0,0],[0,0],[0.208,0.67],[0.414,0.475],[0.608,0.263],[0.8,0],[0.639,-0.284],[0.448,-0.506],[0.243,-0.701],[0,-0.841],[0,0],[-0.25,-0.653],[-0.475,-0.485],[-0.68,-0.28],[-0.861,0]],"o":[[0.455,-0.113],[0.362,-0.188],[0.267,-0.239],[0,0],[-0.328,0.424],[-0.458,0.202],[-0.383,0],[-0.308,-0.116],[-0.229,-0.208],[-0.147,-0.294],[0,0],[0,0],[0,-0.82],[-0.209,-0.67],[-0.414,-0.475],[-0.609,-0.263],[-0.793,0],[-0.639,0.284],[-0.448,0.506],[-0.243,0.701],[0,0],[0,0.745],[0.249,0.653],[0.475,0.485],[0.68,0.28],[0.54,0]],"v":[[50.977,0.036],[52.203,-0.415],[53.146,-1.056],[53.812,-1.794],[52.356,-3.425],[51.177,-2.487],[49.68,-2.184],[48.645,-2.358],[47.84,-2.845],[47.276,-3.599],[46.983,-4.583],[54.048,-4.583],[54.048,-5.845],[53.736,-8.08],[52.802,-9.798],[51.27,-10.905],[49.157,-11.3],[47.009,-10.874],[45.379,-9.69],[44.343,-7.88],[43.979,-5.568],[43.979,-5.168],[44.353,-3.071],[45.44,-1.364],[47.173,-0.215],[49.485,0.205]],"c":true},"ix":2},"nm":"e","mn":"ADBE Vector Shape - Group","hd":false},{"ind":1,"ty":"sh","ix":2,"ks":{"a":0,"k":{"i":[[-0.25,-0.103],[-0.161,-0.185],[-0.079,-0.253],[-0.007,-0.294],[0,0],[0,0],[-0.109,0.28],[-0.174,0.202],[-0.243,0.113],[-0.321,0]],"o":[[0.249,0.103],[0.161,0.185],[0.079,0.253],[0,0],[0,0],[0.048,-0.342],[0.109,-0.28],[0.174,-0.202],[0.243,-0.113],[0.342,0]],"v":[[50.034,-8.747],[50.649,-8.316],[51.008,-7.66],[51.136,-6.839],[51.136,-6.604],[47.014,-6.604],[47.25,-7.537],[47.676,-8.26],[48.301,-8.731],[49.147,-8.9]],"c":true},"ix":2},"nm":"e","mn":"ADBE Vector Shape - Group","hd":false},{"ty":"mm","mm":1,"nm":"合并路径 1","mn":"ADBE Vector Filter - Merge","hd":false},{"ty":"fl","c":{"a":0,"k":[1,1,1,1],"ix":4},"o":{"a":0,"k":100,"ix":5},"r":1,"nm":"填充 1","mn":"ADBE Vector Graphic - Fill","hd":false},{"ty":"tr","p":{"a":0,"k":[0,0],"ix":2},"a":{"a":0,"k":[0,0],"ix":1},"s":{"a":0,"k":[100,100],"ix":3},"r":{"a":0,"k":0,"ix":6},"o":{"a":0,"k":100,"ix":7},"sk":{"a":0,"k":0,"ix":4},"sa":{"a":0,"k":0,"ix":5},"nm":"变换"}],"nm":"e","np":5,"cix":2,"ix":6,"mn":"ADBE Vector Group","hd":false},{"ty":"gr","it":[{"ind":0,"ty":"sh","ix":1,"ks":{"a":0,"k":{"i":[[0.29,-0.215],[0.567,0],[0.243,0.062],[0.185,0.13],[0.113,0.209],[0.014,0.287],[0,0],[-0.205,-0.444],[-0.407,-0.355],[-0.595,-0.219],[-0.779,0],[-0.574,0.171],[-0.407,0.301],[-0.219,0.414],[0,0.492],[0.212,0.386],[0.373,0.27],[0.513,0.171],[0.601,0.116],[0.263,0.089],[0.161,0.106],[0.072,0.127],[0,0.164],[-0.273,0.226],[-0.499,0],[-0.273,-0.277],[0,-0.424],[0,0],[0.215,0.438],[0.4,0.318],[0.574,0.178],[0.718,0],[0.55,-0.185],[0.379,-0.318],[0.202,-0.417],[0,-0.465],[-0.198,-0.362],[-0.352,-0.273],[-0.482,-0.185],[-0.567,-0.123],[-0.294,-0.103],[-0.171,-0.113],[-0.062,-0.13],[0,-0.157]],"o":[[-0.291,0.215],[-0.267,0],[-0.243,-0.062],[-0.185,-0.13],[-0.113,-0.208],[0,0],[0,0.451],[0.205,0.444],[0.407,0.356],[0.595,0.219],[0.711,0],[0.574,-0.171],[0.407,-0.301],[0.219,-0.414],[0,-0.547],[-0.212,-0.386],[-0.373,-0.27],[-0.513,-0.171],[-0.383,-0.075],[-0.263,-0.089],[-0.161,-0.106],[-0.072,-0.126],[0,-0.349],[0.273,-0.226],[0.581,0],[0.273,0.277],[0,0],[0,-0.519],[-0.215,-0.437],[-0.4,-0.318],[-0.574,-0.178],[-0.691,0],[-0.55,0.185],[-0.379,0.318],[-0.202,0.417],[0,0.479],[0.198,0.362],[0.352,0.273],[0.482,0.185],[0.465,0.096],[0.294,0.103],[0.171,0.113],[0.062,0.13],[0,0.349]],"v":[[61.303,-2.22],[60.016,-1.897],[59.252,-1.989],[58.611,-2.276],[58.165,-2.784],[57.976,-3.527],[55.166,-3.527],[55.474,-2.184],[56.391,-0.984],[57.894,-0.123],[59.955,0.205],[61.882,-0.051],[63.354,-0.759],[64.292,-1.83],[64.62,-3.189],[64.302,-4.589],[63.426,-5.573],[62.098,-6.234],[60.426,-6.665],[59.457,-6.911],[58.822,-7.203],[58.473,-7.552],[58.365,-7.988],[58.775,-8.849],[59.934,-9.188],[61.216,-8.772],[61.626,-7.721],[64.589,-7.721],[64.266,-9.157],[63.344,-10.29],[61.882,-11.033],[59.944,-11.3],[58.083,-11.023],[56.689,-10.269],[55.817,-9.167],[55.515,-7.844],[55.812,-6.583],[56.637,-5.629],[57.888,-4.942],[59.462,-4.481],[60.601,-4.184],[61.298,-3.861],[61.646,-3.497],[61.739,-3.066]],"c":true},"ix":2},"nm":"s","mn":"ADBE Vector Shape - Group","hd":false},{"ty":"fl","c":{"a":0,"k":[1,1,1,1],"ix":4},"o":{"a":0,"k":100,"ix":5},"r":1,"nm":"填充 1","mn":"ADBE Vector Graphic - Fill","hd":false},{"ty":"tr","p":{"a":0,"k":[0,0],"ix":2},"a":{"a":0,"k":[0,0],"ix":1},"s":{"a":0,"k":[100,100],"ix":3},"r":{"a":0,"k":0,"ix":6},"o":{"a":0,"k":100,"ix":7},"sk":{"a":0,"k":0,"ix":4},"sa":{"a":0,"k":0,"ix":5},"nm":"变换"}],"nm":"s","np":3,"cix":2,"ix":7,"mn":"ADBE Vector Group","hd":false},{"ty":"gr","it":[{"ind":0,"ty":"sh","ix":1,"ks":{"a":0,"k":{"i":[[0,0],[0,0],[0,0],[0,0],[0,0],[0,0],[-0.15,-0.417],[-0.277,-0.26],[-0.39,-0.12],[-0.485,0],[-0.291,0.051],[-0.246,0.075],[0,0],[0.147,-0.014],[0.178,0],[0.14,0.031],[0.096,0.086],[0.048,0.15],[0,0.232],[0,0],[0,0],[0,0],[0,0],[0,0]],"o":[[0,0],[0,0],[0,0],[0,0],[0,0],[0,0.588],[0.15,0.417],[0.277,0.26],[0.39,0.12],[0.369,0],[0.29,-0.051],[0,0],[-0.109,0.021],[-0.147,0.014],[-0.191,0],[-0.14,-0.031],[-0.096,-0.085],[-0.048,-0.15],[0,0],[0,0],[0,0],[0,0],[0,0],[0,0]],"v":[[67.112,-13.822],[67.112,-11.095],[65.492,-11.095],[65.492,-8.921],[67.112,-8.921],[67.112,-3.066],[67.337,-1.559],[67.978,-0.543],[68.978,0.026],[70.291,0.205],[71.28,0.128],[72.085,-0.062],[72.085,-2.307],[71.7,-2.256],[71.213,-2.235],[70.716,-2.281],[70.362,-2.456],[70.147,-2.81],[70.075,-3.384],[70.075,-8.921],[71.972,-8.921],[71.972,-11.095],[70.075,-11.095],[70.075,-13.822]],"c":true},"ix":2},"nm":"t","mn":"ADBE Vector Shape - Group","hd":false},{"ty":"fl","c":{"a":0,"k":[1,1,1,1],"ix":4},"o":{"a":0,"k":100,"ix":5},"r":1,"nm":"填充 1","mn":"ADBE Vector Graphic - Fill","hd":false},{"ty":"tr","p":{"a":0,"k":[0,0],"ix":2},"a":{"a":0,"k":[0,0],"ix":1},"s":{"a":0,"k":[100,100],"ix":3},"r":{"a":0,"k":0,"ix":6},"o":{"a":0,"k":100,"ix":7},"sk":{"a":0,"k":0,"ix":4},"sa":{"a":0,"k":0,"ix":5},"nm":"变换"}],"nm":"t","np":3,"cix":2,"ix":8,"mn":"ADBE Vector Group","hd":false},{"ty":"gr","it":[{"ind":0,"ty":"sh","ix":1,"ks":{"a":0,"k":{"i":[[0.29,-0.215],[0.567,0],[0.243,0.062],[0.185,0.13],[0.113,0.209],[0.014,0.287],[0,0],[-0.205,-0.444],[-0.407,-0.355],[-0.595,-0.219],[-0.779,0],[-0.574,0.171],[-0.407,0.301],[-0.219,0.414],[0,0.492],[0.212,0.386],[0.373,0.27],[0.513,0.171],[0.601,0.116],[0.263,0.089],[0.161,0.106],[0.072,0.127],[0,0.164],[-0.273,0.226],[-0.499,0],[-0.273,-0.277],[0,-0.424],[0,0],[0.215,0.438],[0.4,0.318],[0.574,0.178],[0.718,0],[0.55,-0.185],[0.379,-0.318],[0.202,-0.417],[0,-0.465],[-0.198,-0.362],[-0.352,-0.273],[-0.482,-0.185],[-0.567,-0.123],[-0.294,-0.103],[-0.171,-0.113],[-0.062,-0.13],[0,-0.157]],"o":[[-0.291,0.215],[-0.267,0],[-0.243,-0.062],[-0.185,-0.13],[-0.113,-0.208],[0,0],[0,0.451],[0.205,0.444],[0.407,0.356],[0.595,0.219],[0.711,0],[0.574,-0.171],[0.407,-0.301],[0.219,-0.414],[0,-0.547],[-0.212,-0.386],[-0.373,-0.27],[-0.513,-0.171],[-0.383,-0.075],[-0.263,-0.089],[-0.161,-0.106],[-0.072,-0.126],[0,-0.349],[0.273,-0.226],[0.581,0],[0.273,0.277],[0,0],[0,-0.519],[-0.215,-0.437],[-0.4,-0.318],[-0.574,-0.178],[-0.691,0],[-0.55,0.185],[-0.379,0.318],[-0.202,0.417],[0,0.479],[0.198,0.362],[0.352,0.273],[0.482,0.185],[0.465,0.096],[0.294,0.103],[0.171,0.113],[0.062,0.13],[0,0.349]],"v":[[79.196,-2.22],[77.909,-1.897],[77.145,-1.989],[76.504,-2.276],[76.058,-2.784],[75.869,-3.527],[73.059,-3.527],[73.367,-2.184],[74.284,-0.984],[75.787,-0.123],[77.848,0.205],[79.775,-0.051],[81.247,-0.759],[82.185,-1.83],[82.513,-3.189],[82.195,-4.589],[81.319,-5.573],[79.991,-6.234],[78.319,-6.665],[77.35,-6.911],[76.715,-7.203],[76.366,-7.552],[76.258,-7.988],[76.668,-8.849],[77.827,-9.188],[79.109,-8.772],[79.519,-7.721],[82.482,-7.721],[82.159,-9.157],[81.237,-10.29],[79.775,-11.033],[77.837,-11.3],[75.976,-11.023],[74.582,-10.269],[73.71,-9.167],[73.408,-7.844],[73.705,-6.583],[74.531,-5.629],[75.781,-4.942],[77.355,-4.481],[78.494,-4.184],[79.191,-3.861],[79.54,-3.497],[79.632,-3.066]],"c":true},"ix":2},"nm":"s","mn":"ADBE Vector Shape - Group","hd":false},{"ty":"fl","c":{"a":0,"k":[1,1,1,1],"ix":4},"o":{"a":0,"k":100,"ix":5},"r":1,"nm":"填充 1","mn":"ADBE Vector Graphic - Fill","hd":false},{"ty":"tr","p":{"a":0,"k":[0,0],"ix":2},"a":{"a":0,"k":[0,0],"ix":1},"s":{"a":0,"k":[100,100],"ix":3},"r":{"a":0,"k":0,"ix":6},"o":{"a":0,"k":100,"ix":7},"sk":{"a":0,"k":0,"ix":4},"sa":{"a":0,"k":0,"ix":5},"nm":"变换"}],"nm":"s","np":3,"cix":2,"ix":9,"mn":"ADBE Vector Group","hd":false}],"ip":0,"op":1001,"st":0,"bm":0}],"markers":[]}